Workbook

Sheet 1.Data
C1: 1G1T1C 1.Data
G2: Matriz ID: | H2: 1g1t1c (G2-T1-C1)
G3: Etapa: | H3: T1 - Diagnóstico Base | K3: Proyecto: | L3: Dossier Analítico NEX_ORD
C4: SIMULACIÓN IN SILICO Datos Anonimizados | G4: Motor Core: | H4: NEX_ORD Platinum v6.0 | K4: Analizado: | L4: 260829_154156
G5: Path Audit: | H5: .../05_Output/FULL_TABLES_1g1t1c.xlsx | K5: Protocolo: | L5: DOI 10.5281/zenodo.189416.1
A7: ► 1.01 DATOS RAW
A9: IDENTIFICACIÓN Y METADATOS | F9: ORDENACION DE ELECCIONES (BREVE) | K9: MORENO | O9: META | Q9: VARIABLES COMPLEMENTARIAS | AA9: ADJETIVOS AAG
A10: Nom | B10: IDi | C10: IDm | D10: Criterio | E10: GRUMO | F10: 1º | G10: 2º | H10: 3º | I10: 4º | J10: 5º | K10: E | L10: R | M10: pE | N10: pR | O10: aE | P10: oE | Q10: SX | R10: ED | S10: ORIG | T10: ANT | U10: ORIEN | V10: IMPL | W10: PRES | X10: ROL | Y10: REND | Z10: COM | AA10: claro | AB10: coherente | AC10: flexible | AD10: consensuado | AE10: productivo | AF10: ordenado | AG10: activo | AH10: ejemplar | AI10: abierto | AJ10: crítico | AK10: perceptivo | AL10: expresivo | AM10: amistoso | AN10: leal | AO10: colaborador | AP10: tolerante
A11: 1 | B11: 1 | C11: 1g1t1c | D11: Tarea | E11: 1 | F11: 1 | G11: 2 | H11: 3 | I11: 4 | J11: 5 | K11: 1, 2 | L11: 5, 4 | M11: 1 | N11: 5 | O11: 1 | P11: 5 | Q11: 1 | R11: 2 | S11: 1 | T11: 2 | U11: 1 | V11: 2 | W11: 1 | X11: 2 | Y11: 3 | Z11: 3 | AA11: 3 | AB11: 3 | AC11: 3 | AD11: 4 | AE11: 3 | AF11: 3 | AG11: 4 | AH11: 3 | AI11: 3 | AJ11: 3 | AK11: 3 | AL11: 3 | AM11: 3 | AN11: 2 | AO11: 2 | AP11: 3
A12: 2 | B12: 2 | C12: 1g1t1c | D12: Tarea | E12: 1 | F12: 3 | G12: 1 | H12: 2 | I12: 5 | J12: 4 | K12: 3, 1 | L12: 4, 5 | M12: 3 | N12: 4 | O12: 3 | P12: 4 | Q12: 2 | R12: 2 | S12: 1 | T12: 2 | U12: 1 | V12: 2 | W12: 1 | X12: 1 | Y12: 2 | Z12: 2 | AA12: 3 | AB12: 3 | AC12: 3 | AD12: 2 | AE12: 4 | AF12: 3 | AG12: 3 | AH12: 2 | AI12: 3 | AJ12: 3 | AK12: 3 | AL12: 3 | AM12: 3 | AN12: 3 | AO12: 3 | AP12: 4
A13: 3 | B13: 3 | C13: 1g1t1c | D13: Tarea | E13: 1 | F13: 2 | G13: 3 | H13: 1 | I13: 5 | J13: 4 | K13: 2, 3 | L13: 4, 5 | M13: 2 | N13: 4 | O13: 2 | P13: 4 | Q13: 1 | R13: 2 | S13: 1 | T13: 2 | U13: 1 | V13: 2 | W13: 1 | X13: 1 | Y13: 2 | Z13: 2 | AA13: 3 | AB13: 3 | AC13: 3 | AD13: 3 | AE13: 3 | AF13: 2 | AG13: 2 | AH13: 3 | AI13: 3 | AJ13: 3 | AK13: 3 | AL13: 3 | AM13: 2 | AN13: 3 | AO13: 3 | AP13: 3
A14: 4 | B14: 4 | C14: 1g1t1c | D14: Tarea | E14: 2 | F14: 4 | G14: 5 | H14: 1 | I14: 2 | J14: 3 | K14: 4, 5 | L14: 3, 2 | M14: 4 | N14: 3 | O14: 4 | P14: 3 | Q14: 2 | R14: 2 | S14: 1 | T14: 2 | U14: 1 | V14: 2 | W14: 1 | X14: 1 | Y14: 2 | Z14: 2 | AA14: 7 | AB14: 6 | AC14: 7 | AD14: 7 | AE14: 7 | AF14: 7 | AG14: 7 | AH14: 7 | AI14: 6 | AJ14: 7 | AK14: 7 | AL14: 7 | AM14: 7 | AN14: 7 | AO14: 6 | AP14: 6
A15: 5 | B15: 5 | C15: 1g1t1c | D15: Tarea | E15: 2 | F15: 5 | G15: 4 | H15: 2 | I15: 3 | J15: 1 | K15: 5, 4 | L15: 1, 3 | M15: 5 | N15: 1 | O15: 5 | P15: 1 | Q15: 1 | R15: 2 | S15: 1 | T15: 2 | U15: 1 | V15: 2 | W15: 1 | X15: 1 | Y15: 2 | Z15: 2 | AA15: 3 | AB15: 4 | AC15: 3 | AD15: 3 | AE15: 3 | AF15: 3 | AG15: 3 | AH15: 4 | AI15: 3 | AJ15: 4 | AK15: 2 | AL15: 3 | AM15: 3 | AN15: 3 | AO15: 3 | AP15: 2
A18: ► 1.02 MATRIZ SMIb instrumental
A20: ID_Sujeto | B20: 1 | C20: 2 | D20: 3 | E20: 4 | F20: 5
A21: 1 | B21: AAAA | C21: 0BB0 | D21: 0000 | E21: 0b00 | F21: aaaa
A22: 2 | B22: 0BB0 | C22: 0000 | D22: AAAA | E22: aaa0 | F22: 0b00
A23: 3 | B23: 0000 | C23: AAAA | D23: 0BB0 | E23: aaaa | F23: 0bb0
A24: 4 | B24: 00c0 | C24: 0baa | D24: aabb | E24: AAAA | F24: 0BB0
A25: 5 | B25: aaaa | C25: 00b0 | D25: 0bc0 | E25: 0BB0 | F25: AAAA
A28: ► 1.03 MATRIZ SMIa integrada | H28: DADAS
A30: SMIa | B30: 1 | C30: 2 | D30: 3 | E30: 4 | F30: 5 | H30: E | I30: ¿ | J30: R | K30: < | L30: ¡ | M30: [
A31: 1 | B31: <Ee> | C31: ¡Ee! | D31: ¡¿?! | E31: ¡R?! | F31: [Rr] | H31: 2 | I31: 1 | J31: 2 | K31: 1 | L31: 3 | M31: 1
A32: 2 | B32: ¡Ee! | C32: <Ee> | D32: <Ee> | E32: [Rr! | F32: ¡R?! | H32: 3 | I32: 0 | J32: 2 | K32: 2 | L32: 2 | M32: 1
A33: 3 | B33: ¡¿?! | C33: <Ee> | D33: ¡Ee! | E33: [Rr] | F33: ¡Rr! | H33: 2 | I33: 1 | J33: 2 | K33: 1 | L33: 3 | M33: 1
A34: 4 | B34: ¡¿r! | C34: ¡Rr] | D34: [Rr] | E34: <Ee> | F34: ¡Ee! | H34: 2 | I34: 1 | J34: 2 | K34: 1 | L34: 3 | M34: 1
A35: 5 | B35: [Rr] | C35: ¡¿r! | D35: ¡Rr! | E35: ¡Ee! | F35: <Ee> | H35: 2 | I35: 1 | J35: 2 | K35: 1 | L35: 3 | M35: 1
G36: SUM | H36: 11 | I36: 4 | J36: 10 | K36: 6 | L36: 14 | M36: 5
A38: Recibidas | B38: 1 | C38: 2 | D38: 3 | E38: 4 | F38: 5 | G38: SUM | I38: SMIa. Explicación
A39: e | B39: 2 | C39: 3 | D39: 2 | E39: 2 | F39: 2 | G39: 11 | J39: DA | L39: RECIBE
A40: ? | B40: 1 | C40: 0 | D40: 1 | E40: 1 | F40: 1 | G40: 4 | I40: tipo | J40: PERCEPCION | K40: REAL | L40: REAL | M40: PERCEPCION
A41: r | B41: 2 | C41: 2 | D41: 2 | E41: 2 | F41: 2 | G41: 10 | I41: elige | J41: < | K41: E | L41: e | M41: >
A42: > | B42: 1 | C42: 2 | D42: 1 | E42: 1 | F42: 1 | G42: 6 | I42: indiferencia | J42: ¡ | K42: ¿ | L42: ? | M42: !
A43: ! | B43: 3 | C43: 2 | D43: 3 | E43: 3 | F43: 3 | G43: 14 | I43: relega | J43: [ | K43: R | L43: r | M43: ]
A44: ] | B44: 1 | C44: 1 | D44: 1 | E44: 1 | F44: 1 | G44: 5
I46: ► 1.05 TOTALES DE GRUPO
A47: ► 1.04 RECUENTOS especiales
J48: % grupales | K48: concepto
A49: Reciprocid | B49: 1 | C49: 2 | D49: 3 | E49: 4 | F49: 5 | G49: SUM | I49: (<)+E | J49: =IFERROR((K$36+H$36)/(K$36+L$36+M$36+H$36+I$36+J$36)*100, 0) -> 34 | K49: Preferencias +
A50: Ee | B50: 2 | C50: 3 | D50: 2 | E50: 2 | F50: 2 | G50: 11 | I50: (¡)+(¿) | J50: =IFERROR((L$36+I$36)/(K$36+L$36+M$36+H$36+I$36+J$36)*100, 0) -> 36 | K50: Indiferencias
A51: ¿? | B51: 1 | D51: 1 | G51: 2 | I51: ([)+R | J51: =IFERROR((M$36+J$36)/(K$36+L$36+M$36+H$36+I$36+J$36)*100, 0) -> 30 | K51: Preferencias -
A52: Rr | B52: 1 | C52: 1 | D52: 2 | E52: 2 | F52: 2 | G52: 8 | J52: =SUM(J49:J51) -> 100
A53: <> | G53: 0 | I53: (<)+E / (<E+[R)*100 | J53: =IFERROR((K$36+H$36)/((K$36+L$36+M$36+H$36+I$36+J$36)-L$36-I$36)*100, 0) -> 53.125 | K53: Ratio +
A54: ¡! | G54: 0 | I54: ([)+R / (<E+[R)*100 | J54: =IFERROR((M$36+J$36)/((K$36+L$36+M$36+H$36+I$36+J$36)-L$36-I$36)*100, 0) -> 46.875 | K54: Ratio -
A55: [] | G55: 0
I56: (<..>) + (Ee) | J56: =IFERROR((6+11)/(K$36+L$36+M$36+H$36+I$36+J$36)*100, 0) -> 34 | K56: Reciprocidad+
I57: (¡..!) + (¿?) | J57: =IFERROR((0+2)/(K$36+L$36+M$36+H$36+I$36+J$36)*100, 0) -> 4 | K57: Reciprocidad =
A58: Oposición | B58: 1 | C58: 2 | D58: 3 | E58: 4 | F58: 5 | G58: SUM | I58: ([..]) + (Rr) | J58: =IFERROR((4+8)/(K$36+L$36+M$36+H$36+I$36+J$36)*100, 0) -> 24 | K58: Reciprocidad -
A59: Er | G59: 0 | I59: (Er)+(<..]) | J59: =IFERROR((0+0)/(K$36+L$36+M$36+H$36+I$36+J$36)*100, 0) -> 0 | K59: Oposición de sentimientos
A60: Re | G60: 0
A61: <] | G61: 0 | I61: (<.?) 0.5 + (<.r) 1.0 | J61: =IFERROR((0)/(K$36+L$36+M$36+H$36+I$36+J$36)*100, 0) -> 0 | K61: ALI+ (Ilusión Afectiva)
A62: [> | G62: 0 | I62: ([.?) 0.5 + ([.e) 1.0 | J62: =IFERROR((0)/(K$36+L$36+M$36+H$36+I$36+J$36)*100, 0) -> 0 | K62: ALI- (Paranoia/Persecución)
I63: ALI+ + ALI- | J63: =IFERROR((0)/(K$36+L$36+M$36+H$36+I$36+J$36)*100, 0) -> 0 | K63: ALI Total (Alienación Global)
A65: 2.02: NUMERALIZACION FIGURAS
A66: FIGURAS | B66: e> | D66: e! | F66: e] | H66: ?> | J66: ?! | L66: ?] | N66: r> | P66: r! | R66: r]
A67: <E | B67: 81 | C67: <Ee> | D67: 80 | E67: <Ee! | F67: 78 | G67: <Ee] | H67: 75 | I67: <E?> | J67: 71 | K67: <E?! | L67: 66 | M67: <E?] | N67: 60 | O67: <Er> | P67: 53 | Q67: <Er! | R67: 45 | S67: <Er]
A68: ¡E | B68: 79 | C68: ¡Ee> | D68: 77 | E68: ¡Ee! | F68: 74 | G68: ¡Ee] | H68: 70 | I68: ¡E?> | J68: 65 | K68: ¡E?! | L68: 59 | M68: ¡E?] | N68: 52 | O68: ¡Er> | P68: 44 | Q68: ¡Er! | R68: 36 | S68: ¡Er]
A69: [E | B69: 76 | C69: [Ee> | D69: 73 | E69: [Ee! | F69: 69 | G69: [Ee] | H69: 64 | I69: [E?> | J69: 58 | K69: [E?! | L69: 51 | M69: [E?] | N69: 43 | O69: [Er> | P69: 35 | Q69: [Er! | R69: 28 | S69: [Er]
A70: <¿ | B70: 72 | C70: <¿e> | D70: 68 | E70: <¿e! | F70: 63 | G70: <¿e] | H70: 57 | I70: <¿?> | J70: 50 | K70: <¿?! | L70: 42 | M70: <¿?] | N70: 34 | O70: <¿r> | P70: 27 | Q70: <¿r! | R70: 21 | S70: <¿r]
A71: ¡¿ | B71: 67 | C71: ¡¿e> | D71: 62 | E71: ¡¿e! | F71: 56 | G71: ¡¿e] | H71: 49 | I71: ¡¿?> | J71: 41 | K71: ¡¿?! | L71: 33 | M71: ¡¿?] | N71: 26 | O71: ¡¿r> | P71: 20 | Q71: ¡¿r! | R71: 15 | S71: ¡¿r]
A72: [¿ | B72: 61 | C72: [¿e> | D72: 55 | E72: [¿e! | F72: 48 | G72: [¿e] | H72: 40 | I72: [¿?> | J72: 32 | K72: [¿?! | L72: 25 | M72: [¿?] | N72: 19 | O72: [¿r> | P72: 14 | Q72: [¿r! | R72: 10 | S72: [¿r]
A73: <R | B73: 54 | C73: <Re> | D73: 47 | E73: <Re! | F73: 39 | G73: <Re] | H73: 31 | I73: <R?> | J73: 24 | K73: <R?! | L73: 18 | M73: <R?] | N73: 13 | O73: <Rr> | P73: 9 | Q73: <Rr! | R73: 6 | S73: <Rr]
A74: ¡R | B74: 46 | C74: ¡Re> | D74: 38 | E74: ¡Re! | F74: 30 | G74: ¡Re] | H74: 23 | I74: ¡R?> | J74: 17 | K74: ¡R?! | L74: 12 | M74: ¡R?] | N74: 8 | O74: ¡Rr> | P74: 5 | Q74: ¡Rr! | R74: 3 | S74: ¡Rr]
A75: [R | B75: 37 | C75: [Re> | D75: 29 | E75: [Re! | F75: 22 | G75: [Re] | H75: 16 | I75: [R?> | J75: 11 | K75: [R?! | L75: 7 | M75: [R?] | N75: 4 | O75: [Rr> | P75: 2 | Q75: [Rr! | R75: 1 | S75: [Rr]
A78: ► 1.06 TOPOGRAFÍA PONDERADA BREVE (MATRIZ C)
B79: 1 | C79: 2 | D79: 3 | E79: 4 | F79: 5 | G79: Suma | H79: Media | I79: DT | J79: %
A80: 1 | B80: 1 | C80: 0.57434918 | D80: 0.41524365 | E80: 0.32987698 | F80: 0.27594593 | G80: =SUM(B80:F80) -> 2.5954157 | H80: =AVERAGE(B80:F80) -> 0.51908315 | I80: =stdev.s(B80:F80) -> 0.2915616 | J80: =IF(G85=0,0,G80/G85) -> 0.2
A81: 2 | B81: 0.41524365 | C81: 1 | D81: 0.57434918 | E81: 0.27594593 | F81: 0.32987698 | G81: =SUM(B81:F81) -> 2.5954157 | H81: =AVERAGE(B81:F81) -> 0.51908315 | I81: =stdev.s(B81:F81) -> 0.2915616 | J81: =IF(G85=0,0,G81/G85) -> 0.2
A82: 3 | B82: 0.57434918 | C82: 0.41524365 | D82: 1 | E82: 0.27594593 | F82: 0.32987698 | G82: =SUM(B82:F82) -> 2.5954157 | H82: =AVERAGE(B82:F82) -> 0.51908315 | I82: =stdev.s(B82:F82) -> 0.2915616 | J82: =IF(G85=0,0,G82/G85) -> 0.2
A83: 4 | B83: 0.32987698 | C83: 0.27594593 | D83: 1 | E83: 0.57434918 | F83: 0.41524365 | G83: =SUM(B83:F83) -> 2.5954157 | H83: =AVERAGE(B83:F83) -> 0.51908315 | I83: =stdev.s(B83:F83) -> 0.2915616 | J83: =IF(G85=0,0,G83/G85) -> 0.2
A84: 5 | B84: 0.27594593 | C84: 0.32987698 | D84: 0.57434918 | E84: 0.41524365 | F84: 1 | G84: =SUM(B84:F84) -> 2.5954157 | H84: =AVERAGE(B84:F84) -> 0.51908315 | I84: =stdev.s(B84:F84) -> 0.2915616 | J84: =IF(G85=0,0,G84/G85) -> 0.2
A85: Suma | B85: =SUM(B80:B84) -> 2.5954157 | C85: =SUM(C80:C84) -> 2.5954157 | D85: =SUM(D80:D84) -> 3.563942 | E85: =SUM(E80:E84) -> 1.8713617 | F85: =SUM(F80:F84) -> 2.3509435 | G85: =SUM(B80:F84) -> 12.977079
A86: Media | B86: =AVERAGE(B80:B84) -> 0.51908315 | C86: =AVERAGE(C80:C84) -> 0.51908315 | D86: =AVERAGE(D80:D84) -> 0.7127884 | E86: =AVERAGE(E80:E84) -> 0.37427233 | F86: =AVERAGE(F80:F84) -> 0.47018871 | H86: =AVERAGE(B80:F84) -> 0.51908315
A87: DT | B87: =stdev.s(B80:B84) -> 0.2915616 | C87: =stdev.s(C80:C84) -> 0.2915616 | D87: =stdev.s(D80:D84) -> 0.27011327 | E87: =stdev.s(E80:E84) -> 0.12551544 | F87: =stdev.s(F80:F84) -> 0.30034313 | I87: =stdev.s(B80:F84) -> 0.26615811
A88: % | B88: =IF(G85=0,0,B85/G85) -> 0.2 | C88: =IF(G85=0,0,C85/G85) -> 0.2 | D88: =IF(G85=0,0,D85/G85) -> 0.27463361 | E88: =IF(G85=0,0,E85/G85) -> 0.14420516 | F88: =IF(G85=0,0,F85/G85) -> 0.18116123 | J88: 1

Sheet 2.SMIa_Frec
C1: 1G1T1C 2.SMIa_Frec
G2: Matriz ID: | H2: 1g1t1c (G2-T1-C1)
G3: Etapa: | H3: T1 - Diagnóstico Base | K3: Proyecto: | L3: Dossier Analítico NEX_ORD
C4: SIMULACIÓN IN SILICO Datos Anonimizados | G4: Motor Core: | H4: NEX_ORD Platinum v6.0 | K4: Analizado: | L4: 260829_154156
G5: Path Audit: | H5: .../05_Output/FULL_TABLES_1g1t1c.xlsx | K5: Protocolo: | L5: DOI 10.5281/zenodo.189416.1
A7: ► 2.01 2.01: SMIa SOCIOMATRIZ RELACIONAL INTEGRADA
A9: SMIa | B9: 1 | C9: 2 | D9: 3 | E9: 4 | F9: 5
A10: 1 | B10: <Ee> | C10: ¡Ee! | D10: ¡¿?! | E10: ¡R?! | F10: [Rr]
A11: 2 | B11: ¡Ee! | C11: <Ee> | D11: <Ee> | E11: [Rr! | F11: ¡R?!
A12: 3 | B12: ¡¿?! | C12: <Ee> | D12: ¡Ee! | E12: [Rr] | F12: ¡Rr!
A13: 4 | B13: ¡¿r! | C13: ¡Rr] | D13: [Rr] | E13: <Ee> | F13: ¡Ee!
A14: 5 | B14: [Rr] | C14: ¡¿r! | D14: ¡Rr! | E14: ¡Ee! | F14: <Ee>
A17: 2.02: NUMERALIZACION FIGURAS
A18: FIGURAS | B18: e> | D18: e! | F18: e] | H18: ?> | J18: ?! | L18: ?] | N18: r> | P18: r! | R18: r]
A19: <E | B19: 81 | C19: <Ee> | D19: 80 | E19: <Ee! | F19: 78 | G19: <Ee] | H19: 75 | I19: <E?> | J19: 71 | K19: <E?! | L19: 66 | M19: <E?] | N19: 60 | O19: <Er> | P19: 53 | Q19: <Er! | R19: 45 | S19: <Er]
A20: ¡E | B20: 79 | C20: ¡Ee> | D20: 77 | E20: ¡Ee! | F20: 74 | G20: ¡Ee] | H20: 70 | I20: ¡E?> | J20: 65 | K20: ¡E?! | L20: 59 | M20: ¡E?] | N20: 52 | O20: ¡Er> | P20: 44 | Q20: ¡Er! | R20: 36 | S20: ¡Er]
A21: [E | B21: 76 | C21: [Ee> | D21: 73 | E21: [Ee! | F21: 69 | G21: [Ee] | H21: 64 | I21: [E?> | J21: 58 | K21: [E?! | L21: 51 | M21: [E?] | N21: 43 | O21: [Er> | P21: 35 | Q21: [Er! | R21: 28 | S21: [Er]
A22: <¿ | B22: 72 | C22: <¿e> | D22: 68 | E22: <¿e! | F22: 63 | G22: <¿e] | H22: 57 | I22: <¿?> | J22: 50 | K22: <¿?! | L22: 42 | M22: <¿?] | N22: 34 | O22: <¿r> | P22: 27 | Q22: <¿r! | R22: 21 | S22: <¿r]
A23: ¡¿ | B23: 67 | C23: ¡¿e> | D23: 62 | E23: ¡¿e! | F23: 56 | G23: ¡¿e] | H23: 49 | I23: ¡¿?> | J23: 41 | K23: ¡¿?! | L23: 33 | M23: ¡¿?] | N23: 26 | O23: ¡¿r> | P23: 20 | Q23: ¡¿r! | R23: 15 | S23: ¡¿r]
A24: [¿ | B24: 61 | C24: [¿e> | D24: 55 | E24: [¿e! | F24: 48 | G24: [¿e] | H24: 40 | I24: [¿?> | J24: 32 | K24: [¿?! | L24: 25 | M24: [¿?] | N24: 19 | O24: [¿r> | P24: 14 | Q24: [¿r! | R24: 10 | S24: [¿r]
A25: <R | B25: 54 | C25: <Re> | D25: 47 | E25: <Re! | F25: 39 | G25: <Re] | H25: 31 | I25: <R?> | J25: 24 | K25: <R?! | L25: 18 | M25: <R?] | N25: 13 | O25: <Rr> | P25: 9 | Q25: <Rr! | R25: 6 | S25: <Rr]
A26: ¡R | B26: 46 | C26: ¡Re> | D26: 38 | E26: ¡Re! | F26: 30 | G26: ¡Re] | H26: 23 | I26: ¡R?> | J26: 17 | K26: ¡R?! | L26: 12 | M26: ¡R?] | N26: 8 | O26: ¡Rr> | P26: 5 | Q26: ¡Rr! | R26: 3 | S26: ¡Rr]
A27: [R | B27: 37 | C27: [Re> | D27: 29 | E27: [Re! | F27: 22 | G27: [Re] | H27: 16 | I27: [R?> | J27: 11 | K27: [R?! | L27: 7 | M27: [R?] | N27: 4 | O27: [Rr> | P27: 2 | Q27: [Rr! | R27: 1 | S27: [Rr]
A30: ► 2.03 MATRIZ FRECUENCIAS | H30: ► 2.04 REORDENACION SMIa NUMERALIZADA
A32: © | B32: 1 | C32: 2 | D32: 3 | E32: 4 | F32: 5 | I32: <Ee> | L32: ¡Ee! | M32: ¡R?!
A33: 1 | B33: 81 | C33: 77 | D33: 41 | E33: 17 | F33: 1 | H33: <Ee> | I33: 81 | J33: 81 | K33: 81 | L33: 77
A34: 2 | B34: 77 | C34: 81 | D34: 81 | E34: 2 | F34: 17 | I34: 81 | J34: 81 | K34: 77 | M34: 17
A35: 3 | B35: 41 | C35: 81 | D35: 77 | E35: 1 | F35: 5 | I35: 81 | J35: 77 | L35: 17 | M35: 3
A36: 4 | B36: 20 | C36: 3 | D36: 1 | E36: 81 | F36: 77 | H36: ¡Ee! | I36: 77 | J36: 20 | K36: 5 | L36: 2 | M36: 1
A37: 5 | B37: 1 | C37: 20 | D37: 5 | E37: 77 | F37: 81 | H37: ¡¿r! | I37: 20 | J37: 5 | K37: 1 | L37: 1 | M37: 1
A41: ► 2.05 TRANSFORMACION DIRECTA SMIa (nxn) -> FIGURAS (9X9) | M41: ► 2.06 CONCENTRACION DIRECTA
A42: FIGURAS | B42: e> | C42: e! | D42: e] | E42: ?> | F42: ?! | G42: ?] | H42: r> | I42: r! | J42: r] | K42: suma | M42: Frec | N42: e! | O42: ?! | P42: r! | Q42: suma
A43: <E | B43: 6 | K43: 6 | M43: ¡E | N43: 11 | Q43: 11
A44: ¡E | C44: 5 | K44: 5 | M44: ¡¿ | O44: 2 | P44: 2 | Q44: 4
A45: [E | M45: ¡R | O45: 2 | P45: 8 | Q45: 10
A46: <¿ | M46: suma | N46: 11 | O46: 4 | P46: 10 | Q46: ►25.
A47: ¡¿ | F47: 2 | I47: 2 | K47: 4
A48: [¿ | M48: % | N48: e! | O48: ?! | P48: r! | Q48: suma
A49: <R | M49: ¡E | N49: 0.44 | Q49: 0.44
A50: ¡R | F50: 2 | I50: 2 | J50: 1 | K50: 5 | M50: ¡¿ | O50: 0.08 | P50: 0.08 | Q50: 0.16
A51: [R | I51: 1 | J51: 4 | K51: 5 | M51: ¡R | O51: 0.08 | P51: 0.32 | Q51: 0.4
A52: suma | B52: 6 | C52: 5 | F52: 4 | I52: 5 | J52: 5 | K52: ►25. | M52: suma | N52: 0.44 | O52: 0.16 | P52: 0.4 | Q52: ►100%.
A55: ► 2.09 DIFERENCIAS DE PORCENTAJES EN FIGURAS SOCIOMETRICAS AGRUPADAS
B57: ELECCIÓN | C57: INDIFERENCIA | D57: REPULSION | E57: Total
A58: % PREFERENCIAS | B58: =IF(SUM(B43:J51)>0, SUM(B43:J45)/SUM(B43:J51)*100, 0) -> 0 | C58: =IF(SUM(B43:J51)>0, SUM(B46:J48)/SUM(B43:J51)*100, 0) -> 0 | D58: =IF(SUM(B43:J51)>0, SUM(B49:J51)/SUM(B43:J51)*100, 0) -> 0 | E58: 100
A59: % PERCEPCION | B59: =IF(SUM(B43:J51)>0, (SUM(B43:J43)+SUM(B46:J46)+SUM(B49:J49))/SUM(B43:J51)*100, 0) -> 0 | C59: =IF(SUM(B43:J51)>0, (SUM(B44:J44)+SUM(B47:J47)+SUM(B50:J50))/SUM(B43:J51)*100, 0) -> 0 | D59: =IF(SUM(B43:J51)>0, (SUM(B45:J45)+SUM(B48:J48)+SUM(B51:J51))/SUM(B43:J51)*100, 0) -> 0 | E59: 100

Sheet 3.SMIa_Den
C1: 1G1T1C ► 3.SMIa_Den
G2: Matriz ID: | H2: 1g1t1c (G2-T1-C1)
G3: Etapa: | H3: T1 - Diagnóstico Base | K3: Proyecto: | L3: Dossier Analítico NEX_ORD
C4: SIMULACIÓN IN SILICO Datos Anonimizados | G4: Motor Core: | H4: NEX_ORD Platinum v6.0 | K4: Analizado: | L4: 260829_154156
G5: Path Audit: | H5: .../05_Output/FULL_TABLES_1g1t1c.xlsx | K5: Protocolo: | L5: DOI 10.5281/zenodo.189416.1
A7: ► 3.01 SMIa Numerali
A9: © | B9: 1 | D9: 2 | F9: 3 | H9: 4 | J9: 5
A10: 1 | B10: 81 | C10: 1-1 | D10: 77 | E10: 1-2 | F10: 41 | G10: 1-3 | H10: 17 | I10: 1-4 | J10: 1 | K10: 1-5
A11: 2 | B11: 77 | C11: 2-1 | D11: 81 | E11: 2-2 | F11: 81 | G11: 2-3 | H11: 2 | I11: 2-4 | J11: 17 | K11: 2-5
A12: 3 | B12: 41 | C12: 3-1 | D12: 81 | E12: 3-2 | F12: 77 | G12: 3-3 | H12: 1 | I12: 3-4 | J12: 5 | K12: 3-5
A13: 4 | B13: 20 | C13: 4-1 | D13: 3 | E13: 4-2 | F13: 1 | G13: 4-3 | H13: 81 | I13: 4-4 | J13: 77 | K13: 4-5
A14: 5 | B14: 1 | C14: 5-1 | D14: 20 | E14: 5-2 | F14: 5 | G14: 5-3 | H14: 77 | I14: 5-4 | J14: 81 | K14: 5-5
A17: ► 3.02 FIGURAS SOCIOM | M17: ► 3.03 NUMERALIZACION
A19: FIGURAS | B19: e> | C19: e! | D19: e] | E19: ?> | F19: ?! | G19: ?] | H19: r> | I19: r! | J19: r] | M19: FIGURAS | N19: e> | O19: e! | P19: e] | Q19: ?> | R19: ?! | S19: ?] | T19: r> | U19: r! | V19: r]
A20: <E | B20: <Ee> | C20: <Ee! | D20: <Ee] | E20: <E?> | F20: <E?! | G20: <E?] | H20: <Er> | I20: <Er! | J20: <Er] | M20: <E | N20: 81 | O20: 80 | P20: 78 | Q20: 75 | R20: 71 | S20: 66 | T20: 60 | U20: 53 | V20: 45
A21: ¡E | B21: ¡Ee> | C21: ¡Ee! | D21: ¡Ee] | E21: ¡E?> | F21: ¡E?! | G21: ¡E?] | H21: ¡Er> | I21: ¡Er! | J21: ¡Er] | M21: ¡E | N21: 79 | O21: 77 | P21: 74 | Q21: 70 | R21: 65 | S21: 59 | T21: 52 | U21: 44 | V21: 36
A22: [E | B22: [Ee> | C22: [Ee! | D22: [Ee] | E22: [E?> | F22: [E?! | G22: [E?] | H22: [Er> | I22: [Er! | J22: [Er] | M22: [E | N22: 76 | O22: 73 | P22: 69 | Q22: 64 | R22: 58 | S22: 51 | T22: 43 | U22: 35 | V22: 28
A23: <¿ | B23: <¿e> | C23: <¿e! | D23: <¿e] | E23: <¿?> | F23: <¿?! | G23: <¿?] | H23: <¿r> | I23: <¿r! | J23: <¿r] | M23: <¿ | N23: 72 | O23: 68 | P23: 63 | Q23: 57 | R23: 50 | S23: 42 | T23: 34 | U23: 27 | V23: 21
A24: ¡¿ | B24: ¡¿e> | C24: ¡¿e! | D24: ¡¿e] | E24: ¡¿?> | F24: ¡¿?! | G24: ¡¿?] | H24: ¡¿r> | I24: ¡¿r! | J24: ¡¿r] | M24: ¡¿ | N24: 67 | O24: 62 | P24: 56 | Q24: 49 | R24: 41 | S24: 33 | T24: 26 | U24: 20 | V24: 15
A25: [¿ | B25: [¿e> | C25: [¿e! | D25: [¿e] | E25: [¿?> | F25: [¿?! | G25: [¿?] | H25: [¿r> | I25: [¿r! | J25: [¿r] | M25: [¿ | N25: 61 | O25: 55 | P25: 48 | Q25: 40 | R25: 32 | S25: 25 | T25: 19 | U25: 14 | V25: 10
A26: <R | B26: <Re> | C26: <Re! | D26: <Re] | E26: <R?> | F26: <R?! | G26: <R?] | H26: <Rr> | I26: <Rr! | J26: <Rr] | M26: <R | N26: 54 | O26: 47 | P26: 39 | Q26: 31 | R26: 24 | S26: 18 | T26: 13 | U26: 9 | V26: 6
A27: ¡R | B27: ¡Re> | C27: ¡Re! | D27: ¡Re] | E27: ¡R?> | F27: ¡R?! | G27: ¡R?] | H27: ¡Rr> | I27: ¡Rr! | J27: ¡Rr] | M27: ¡R | N27: 46 | O27: 38 | P27: 30 | Q27: 23 | R27: 17 | S27: 12 | T27: 8 | U27: 5 | V27: 3
A28: [R | B28: [Re> | C28: [Re! | D28: [Re] | E28: [R?> | F28: [R?! | G28: [R?] | H28: [Rr> | I28: [Rr! | J28: [Rr] | M28: [R | N28: 37 | O28: 29 | P28: 22 | Q28: 16 | R28: 11 | S28: 7 | T28: 4 | U28: 2 | V28: 1
A31: ► 3.04 TRANSFORMACION | M31: ► 3.05 SUJETOS EN CADA CELDA
A33: FIGURA | B33: e> | C33: e! | D33: e] | E33: ?> | F33: ?! | G33: ?] | H33: r> | I33: r! | J33: r] | K33: suma | M33: ► 3.07 TRANSFORMACION INVERSA SMIa (nxn) -> FIGURAS (9X9) FRECUENCIAS
A34: <E | B34: 6 | K34: 6 | M34: 77 | N34: 1-2 | O34: 2-1 | P34: 3-3 | Q34: 4-5 | R34: 5-4
A35: ¡E | C35: 5 | K35: 5 | M35: FIGURA | N35: e> | O35: ?> | P35: r> | Q35: e! | R35: ?! | S35: r! | T35: e] | U35: ?] | V35: r] | W35: suma
A36: [E | M36: <E | N36: 6 | W36: 6
A37: <¿ | M37: <¿
A38: ¡¿ | F38: 2 | I38: 2 | K38: 4 | M38: <R
A39: [¿ | M39: ¡E | Q39: 5 | W39: 5
A40: <R | M40: ¡¿ | R40: 2 | S40: 2 | W40: 4
A41: ¡R | F41: 2 | I41: 2 | J41: 1 | K41: 5 | M41: ¡R | R41: 2 | S41: 2 | V41: 1 | W41: 5
A42: [R | I42: 1 | J42: 4 | K42: 5 | M42: [E
A43: suma | B43: 6 | C43: 5 | F43: 4 | I43: 5 | J43: 5 | K43: 25 | M43: [¿
M44: [R | S44: 1 | V44: 4 | W44: 5
A45: ► 3.06 3x3 DIRECTA FRECUENCIAS | M45: suma | N45: 6 | Q45: 5 | R45: 4 | S45: 5 | V45: 5 | W45: 25
A47: Frec | B47: e! | C47: ?! | D47: r! | E47: suma | M47: ► 3.08 3x3 INVERSA FRECUENCIAS
A48: ¡E | B48: 11 | E48: 11
A49: ¡¿ | C49: 2 | D49: 2 | E49: 4 | M49: Frec | N49: e! | O49: ?! | P49: r! | Q49: suma
A50: ¡R | C50: 2 | D50: 8 | E50: 10 | M50: ¡E | N50: 6 | Q50: 6
A51: suma | B51: 11 | C51: 4 | D51: 10 | E51: 25 | M51: ¡¿ | O51: 13 | P51: 1 | Q51: 14
M52: ¡R | O52: 1 | P52: 4 | Q52: 5
G53: % | H53: e! | I53: ?! | J53: r! | K53: suma | M53: suma | N53: 6 | O53: 14 | P53: 5 | Q53: 25
G54: <E | H54: 44 | I54: ### | J54: ### | K54: 44
G55: ¡¿ | H55: ### | I55: 8 | J55: 8 | K55: 16 | S55: % | T55: e! | U55: ?! | V55: r! | W55: suma
G56: ¡R | H56: ### | I56: 8 | J56: 32 | K56: 40 | S56: <E | T56: 24 | U56: ### | V56: ### | W56: 24
G57: suma | H57: 44 | I57: 16 | J57: 40 | K57: 100 | S57: ¡¿ | T57: ### | U57: 52 | V57: 4 | W57: 56
S58: ¡R | T58: ### | U58: 4 | V58: 16 | W58: 20
S59: suma | T59: 24 | U59: 56 | V59: 20 | W59: 100
A61: ► 3.09 DENSIDAD DIRECTA A1 | N61: ► 3.11 DENSIDAD INVERSA A1
A63: FIGURA | B63: e> | C63: e! | D63: e] | E63: ?> | F63: ?! | G63: ?] | H63: r> | I63: r! | J63: r] | K63: µ/N | N63: FIGURA | O63: e> | P63: ?> | Q63: r> | R63: e! | S63: ?! | T63: r! | U63: e] | V63: ?] | W63: r] | X63: µ/N
A64: <E | B64: 3.7 | K64: 0.74 | N64: <E | O64: 3.7 | X64: 0.74
A65: ¡E | C65: 1.26 | K65: 0.252 | N65: <¿
A66: [E | N66: <R
A67: <¿ | N67: ¡E | R67: 1.26 | X67: 0.252
A68: ¡¿ | F68: 0 | I68: -0.63 | K68: -0.126 | N68: ¡¿ | S68: 0 | T68: -0.63 | X68: -0.126
A69: [¿ | N69: ¡R | S69: -0.71 | T69: -1.26 | W69: -2.45 | X69: -0.884
A70: <R | N70: [E
A71: ¡R | F71: -0.71 | I71: -1.26 | J71: -2.45 | K71: -0.884 | N71: [¿
A72: [R | I72: -2.97 | J72: -3.2 | K72: -1.234 | N72: [R | T72: -2.97 | W72: -3.2 | X72: -1.234
A73: ► 3.10 3x3 DIRECTA A1 | F73: -0.142 | I73: -0.972 | J73: -1.13 | K73: -1.252 | N73: ► 3.12 3x3 INVERSA A1 | S73: -0.142 | T73: -0.972 | W73: -1.13 | X73: -1.252
A75: Frec | B75: e! | C75: ?! | D75: r! | E75: suma | G75: % | H75: e! | I75: ?! | J75: r! | K75: suma | N75: Frec | O75: e! | P75: ?! | Q75: r! | R75: suma | T75: % | U75: e! | V75: ?! | W75: r! | X75: suma
A76: ¡E | B76: 4.96 | E76: 4.96 | G76: ¡E | H76: 30.65513 | I76: 0 | J76: 0 | K76: 30.65513 | N76: ¡E | O76: 3.7 | R76: 3.7 | T76: <E | U76: 22.867738 | V76: 0 | W76: 0 | X76: 22.867738
A77: ¡¿ | D77: -0.63 | E77: -0.63 | G77: ¡¿ | H77: 0 | I77: 0 | J77: -3.8936959 | K77: -3.8936959 | N77: ¡¿ | P77: -1.34 | Q77: -2.45 | R77: -3.79 | T77: ¡¿ | U77: 0 | V77: -8.2818294 | W77: -15.142151 | X77: -23.42398
A78: ¡R | C78: -0.71 | D78: -9.88 | E78: -10.59 | G78: ¡R | H78: 0 | I78: -4.3881335 | J78: -61.063041 | K78: -65.451174 | N78: ¡R | P78: -2.97 | Q78: -3.2 | R78: -6.17 | T78: ¡R | U78: 0 | V78: -18.355995 | W78: -19.777503 | X78: -38.133498
A79: suma | B79: 4.96 | C79: -0.71 | D79: -10.51 | E79: -6.26 | G79: suma | H79: 30.65513 | I79: -4.3881335 | J79: -64.956737 | K79: -38.68974 | N79: suma | O79: 3.7 | P79: -4.31 | Q79: -5.65 | R79: -6.26 | T79: suma | U79: 22.867738 | V79: -26.637824 | W79: -34.919654 | X79: -38.68974
A83: ► 3.13 DENSIDAD DIRECTA A2 | N83: ► 3.15 DENSIDAD INVERSA A2
A85: FIGURA | B85: e> | C85: e! | D85: e] | E85: ?> | F85: ?! | G85: ?] | H85: r> | I85: r! | J85: r] | K85: µ/N | N85: FIGURA | O85: e> | P85: ?> | Q85: r> | R85: e! | S85: ?! | T85: r! | U85: e] | V85: ?] | W85: r] | X85: µ/N
A86: <E | B86: 2.6333333 | K86: 0.52666667 | N86: <E | O86: 2.6333333 | X86: 0.52666667
A87: ¡E | C87: -0.27 | K87: -0.054 | N87: <¿
A88: [E | N88: <R
A89: <¿ | N89: ¡E | R89: -0.27 | X89: -0.054
A90: ¡¿ | F90: 0 | I90: -0.63 | K90: -0.126 | N90: ¡¿ | S90: 0 | T90: -0.63 | X90: -0.126
A91: [¿ | N91: ¡R | S91: -2.57 | T91: -2.72 | W91: -3.03 | X91: -1.664
A92: <R | N92: [E
A93: ¡R | F93: -2.57 | I93: -2.72 | J93: -3.03 | K93: -1.664 | N93: [¿
A94: [R | I94: -3.02 | J94: -3.21 | K94: -1.246 | N94: [R | T94: -3.02 | W94: -3.21 | X94: -1.246
A95: ► 3.14 3x3 DIRECTA A2 | F95: -0.514 | I95: -1.274 | J95: -1.248 | K95: -2.5633333 | N95: ► 3.16 3x3 INVERSA A2 | S95: -0.514 | T95: -1.274 | W95: -1.248 | X95: -2.5633333
A97: Frec | B97: e! | C97: ?! | D97: r! | E97: suma | G97: % | H97: e! | I97: ?! | J97: r! | K97: suma | N97: Frec | O97: e! | P97: ?! | Q97: r! | R97: suma | T97: % | U97: e! | V97: ?! | W97: r! | X97: suma
A98: ¡E | B98: 2.3633333 | E98: 2.3633333 | G98: ¡E | H98: 13.069124 | I98: 0 | J98: 0 | K98: 13.069124 | N98: ¡E | O98: 2.6333333 | R98: 2.6333333 | T98: <E | U98: 14.562212 | V98: 0 | W98: 0 | X98: 14.562212
A99: ¡¿ | D99: -0.63 | E99: -0.63 | G99: ¡¿ | H99: 0 | I99: 0 | J99: -3.483871 | K99: -3.483871 | N99: ¡¿ | P99: -6.19 | Q99: -3.03 | R99: -9.22 | T99: ¡¿ | U99: 0 | V99: -34.230415 | W99: -16.75576 | X99: -50.986175
A100: ¡R | C100: -2.57 | D100: -11.98 | E100: -14.55 | G100: ¡R | H100: 0 | I100: -14.211982 | J100: -66.248848 | K100: -80.460829 | N100: ¡R | P100: -3.02 | Q100: -3.21 | R100: -6.23 | T100: ¡R | U100: 0 | V100: -16.700461 | W100: -17.751152 | X100: -34.451613
A101: suma | B101: 2.3633333 | C101: -2.57 | D101: -12.61 | E101: -12.816667 | G101: suma | H101: 13.069124 | I101: -14.211982 | J101: -69.732719 | K101: -70.875576 | N101: suma | O101: 2.6333333 | P101: -9.21 | Q101: -6.24 | R101: -12.816667 | T101: suma | U101: 14.562212 | V101: -50.930876 | W101: -34.506912 | X101: -70.875576
A105: ► 3.17 DENSIDAD DIRECTA A3 | N105: ► 3.19 DENSIDAD INVERSA A3
A107: FIGURA | B107: e> | C107: e! | D107: e] | E107: ?> | F107: ?! | G107: ?] | H107: r> | I107: r! | J107: r] | K107: µ/N | N107: FIGURA | O107: e> | P107: ?> | Q107: r> | R107: e! | S107: ?! | T107: r! | U107: e] | V107: ?] | W107: r] | X107: µ/N
A108: <E | B108: 2.6333333 | K108: 0.52666667 | N108: <E | O108: 2.6333333 | X108: 0.52666667
A109: ¡E | C109: -0.27 | K109: -0.054 | N109: <¿
A110: [E | N110: <R
A111: <¿ | N111: ¡E | R111: -0.27 | X111: -0.054
A112: ¡¿ | F112: 0 | I112: -2.625 | K112: -0.525 | N112: ¡¿ | S112: 0 | T112: -2.625 | X112: -0.525
A113: [¿ | N113: ¡R | S113: -0.71 | T113: -2.775 | W113: -2.92 | X113: -1.281
A114: <R | N114: [E
A115: ¡R | F115: -0.71 | I115: -2.775 | J115: -2.92 | K115: -1.281 | N115: [¿
A116: [R | I116: -3.02 | J116: -3.2125 | K116: -1.2465 | N116: [R | T116: -3.02 | W116: -3.2125 | X116: -1.2465
A117: ► 3.18 3x3 DIRECTA A3 | F117: -0.142 | I117: -1.684 | J117: -1.2265 | K117: -2.5798333 | N117: ► 3.20 3x3 INVERSA A3 | S117: -0.142 | T117: -1.684 | W117: -1.2265 | X117: -2.5798333
A119: Frec | B119: e! | C119: ?! | D119: r! | E119: suma | G119: % | H119: e! | I119: ?! | J119: r! | K119: suma | N119: Frec | O119: e! | P119: ?! | Q119: r! | R119: suma | T119: % | U119: e! | V119: ?! | W119: r! | X119: suma
A120: ¡E | B120: 2.3633333 | E120: 2.3633333 | G120: ¡E | H120: 13.009771 | I120: 0 | J120: 0 | K120: 13.009771 | N120: ¡E | O120: 2.6333333 | R120: 2.6333333 | T120: <E | U120: 14.496078 | V120: 0 | W120: 0 | X120: 14.496078
A121: ¡¿ | D121: -2.625 | E121: -2.625 | G121: ¡¿ | H121: 0 | I121: 0 | J121: -14.450204 | K121: -14.450204 | N121: ¡¿ | P121: -6.38 | Q121: -2.92 | R121: -9.3 | T121: ¡¿ | U121: 0 | V121: -35.120877 | W121: -16.074132 | X121: -51.195009
A122: ¡R | C122: -0.71 | D122: -11.9275 | E122: -12.6375 | G122: ¡R | H122: 0 | I122: -3.9084362 | J122: -65.658975 | K122: -69.567411 | N122: ¡R | P122: -3.02 | Q122: -3.2125 | R122: -6.2325 | T122: ¡R | U122: 0 | V122: -16.624616 | W122: -17.684297 | X122: -34.308913
...

Sheet 4.Densidad
C1: 1G1T1C DENSIDAD RELACIONAL
G2: Matriz ID: | H2: 1g1t1c (G2-T1-C1)
G3: Etapa: | H3: T1 - Diagnóstico Base | K3: Proyecto: | L3: Dossier Analítico NEX_ORD
C4: SIMULACIÓN IN SILICO Datos Anonimizados | G4: Motor Core: | H4: NEX_ORD Platinum v6.0 | K4: Analizado: | L4: 260829_154156
G5: Path Audit: | H5: .../05_Output/FULL_TABLES_1g1t1c.xlsx | K5: Protocolo: | L5: DOI 10.5281/zenodo.189416.1
A7: ► TABLA MAESTRA SÍNTESIS DENSIDAD RELACIONAL
F8: A1+A2 | G8: SRC-SDA | H8: A3+A4 | I8: SDA+SRC | J8: |A1|+|A2| | K8: BRC-BDA | L8: |A3|+|A4| | M8: BDA+BRC | N8: BDR-SDR
A9: 1g1t2c | B9: A1 | C9: A2 | D9: A3 | E9: A4 | F9: SDA | G9: Dif | H9: SRC | I9: SDR | J9: BDA | K9: Dif | L9: BRC | M9: BDR | N9: Dif_DR
A10: 1 | B10: 1.83 | C10: -1.92 | D10: -2.025 | E10: 1.83 | F10: =B10+C10 -> -0.09 | G10: =H10-F10 -> -0.105 | H10: =D10+E10 -> -0.195 | I10: =F10+H10 -> -0.285 | J10: 17.81 | K10: =L10-J10 -> 0.105 | L10: 17.915 | M10: =J10+L10 -> 35.725 | N10: =M10-I10 -> 36.01
A11: 2 | B11: 2.32 | C11: -1.735 | D11: -1.71 | E11: 2.255 | F11: =B11+C11 -> 0.585 | G11: =H11-F11 -> -0.04 | H11: =D11+E11 -> 0.545 | I11: =F11+H11 -> 1.13 | J11: 17.135 | K11: =L11-J11 -> 0.04 | L11: 17.175 | M11: =J11+L11 -> 34.31 | N11: =M11-I11 -> 33.18
A12: 3 | B12: 1.24 | C12: -3.04 | D12: -3.1 | E12: 1.235 | F12: =B12+C12 -> -1.8 | G12: =H12-F12 -> -0.065 | H12: =D12+E12 -> -1.865 | I12: =F12+H12 -> -3.665 | J12: 19.52 | K12: =L12-J12 -> 0.065 | L12: 19.585 | M12: =J12+L12 -> 39.105 | N12: =M12-I12 -> 42.77
A13: 4 | B13: -0.88 | C13: -4.945 | D13: -5 | E13: -0.95 | F13: =B13+C13 -> -5.825 | G13: =H13-F13 -> -0.125 | H13: =D13+E13 -> -5.95 | I13: =F13+H13 -> -11.775 | J13: 23.545 | K13: =L13-J13 -> 0.125 | L13: 23.67 | M13: =J13+L13 -> 47.215 | N13: =M13-I13 -> 58.99
A14: 5 | B14: 0.57 | C14: -4.64 | D14: -4.725 | E14: 0.57 | F14: =B14+C14 -> -4.07 | G14: =H14-F14 -> -0.085 | H14: =D14+E14 -> -4.155 | I14: =F14+H14 -> -8.225 | J14: 21.79 | K14: =L14-J14 -> 0.085 | L14: 21.875 | M14: =J14+L14 -> 43.665 | N14: =M14-I14 -> 51.89
A15: Media | B15: =AVERAGE(B10:B14) -> 1.016 | C15: =AVERAGE(C10:C14) -> -3.256 | D15: =AVERAGE(D10:D14) -> -3.312 | E15: =AVERAGE(E10:E14) -> 0.988 | F15: =AVERAGE(F10:F14) -> -2.24 | G15: =AVERAGE(G10:G14) -> -0.084 | H15: =AVERAGE(H10:H14) -> -2.324 | I15: =AVERAGE(I10:I14) -> -4.564 | ... N15: =AVERAGE(N10:N14) -> 44.568
A18: ► 4.01 GRUPO A1-A4 pE/R, E/R, e/r, pe/r | L18: ► 4.02 RESUMEN DE DENSIDADES
A20: A1 | B20: 1 | C20: 2 | D20: 3 | E20: 4 | F20: 5 | G20: SUMA | H20: MEDIA | I20: DT | J20: %_PESO | L20: RESUMEN | M20: SUMA | N20: MEDIA | O20: DT | P20: %_PESO
A21: 1 | B21: 4.44 | C21: 1.26 | D21: 0 | E21: -0.71 | F21: -3.2 | G21: 1.79 | H21: 0.358 | I21: 2.801985 | J21: 35.23622 | L21: A1 | M21: 5.08 | N21: 0.2032 | O21: 2.578638 | P21: 11.852543
A22: 2 | B22: 1.26 | C22: 0 | D22: 4.44 | E22: -2.97 | F22: -0.71 | G22: 2.02 | H22: 0.404 | I22: 2.7299322 | J22: 39.76378 | L22: A2 | M22: -16.28 | N22: -0.6512 | O22: 2.2628218 | P22: -37.984134
A23: 3 | B23: 0 | C23: 4.44 | D23: 1.26 | E23: -3.2 | F23: -1.26 | G23: 1.24 | H23: 0.248 | I23: 2.864493 | J23: 24.409449 | L23: A3 | M23: -16.56 | N23: -0.6624 | O23: 2.2667921 | P23: -38.637424
A24: 4 | B24: -0.63 | C24: -2.45 | D24: -3.2 | E24: 4.44 | F24: 1.26 | G24: -0.58 | H24: -0.116 | I24: 3.0770652 | J24: -11.417323 | L24: A4 | M24: 4.94 | N24: 0.1976 | O24: 2.5841583 | P24: 11.525898
A25: 5 | B25: -3.2 | C25: -0.63 | D25: -1.26 | E25: 1.26 | F25: 4.44 | G25: 0.61 | H25: 0.122 | I25: 2.8918541 | J25: 12.007874
A26: T_COL | B26: 1.87 | C26: 2.62 | D26: 1.24 | E26: -1.18 | F26: 0.53 | G26: 5.08
A27: Media_C | B27: 0.374 | C27: 0.524 | D27: 0.248 | E27: -0.236 | F27: 0.106
A28: DT_C | B28: 2.7945805 | C28: 2.5655272 | D28: 2.864493 | E28: 3.1854246 | F28: 2.8972711
A29: %_PESO | B29: 36.811024 | C29: 51.574803 | D29: 24.409449 | E29: -23.228346 | F29: 10.433071 | G29: 100
A30: DA | B30: 35.23622 | C30: 39.76378 | D30: 24.409449 | E30: -11.417323 | F30: 12.007874
A31: Diferencia | B31: 1.5748031 | C31: 11.811024 | D31: 0 | E31: -11.811024 | F31: -1.5748031
A33: A2 | B33: 1 | C33: 2 | D33: 3 | E33: 4 | F33: 5 | G33: SUMA | H33: MEDIA | I33: DT | J33: %_PESO
A34: 1 | B34: 3.16 | C34: -0.27 | D34: 0 | E34: -2.57 | F34: -3.21 | G34: -2.89 | H34: -0.578 | I34: 2.5148101 | J34: 17.751843
A35: 2 | B35: -0.27 | C35: 0 | D35: 3.16 | E35: -3.02 | F35: -2.57 | G35: -2.7 | H35: -0.54 | I35: 2.4660596 | J35: 16.584767
A36: 3 | B36: 0 | C36: 3.16 | D36: -0.27 | E36: -3.21 | F36: -2.72 | G36: -3.04 | H36: -0.608 | I36: 2.5452249 | J36: 18.673219
A37: 4 | B37: -0.63 | C37: -3.03 | D37: -3.21 | E37: 3.16 | F37: -0.27 | G37: -3.98 | H37: -0.796 | I37: 2.5870988 | J37: 24.447174
A38: 5 | B38: -3.21 | C38: -0.63 | D38: -2.72 | E38: -0.27 | F38: 3.16 | G38: -3.67 | H38: -0.734 | I38: 2.5230993 | J38: 22.542998
A39: T_COL | B39: -0.95 | C39: -0.77 | D39: -3.04 | E39: -5.91 | F39: -5.61 | G39: -16.28
A40: Media_C | B40: -0.19 | C40: -0.154 | D40: -0.608 | E40: -1.182 | F40: -1.122
A41: DT_C | B41: 2.2682041 | C41: 2.2089432 | D41: 2.5452249 | E41: 2.6973265 | F41: 2.6491263
A42: %_PESO | B42: 5.8353808 | C42: 4.7297297 | D42: 18.673219 | E42: 36.302211 | F42: 34.459459 | G42: 100
A43: DA | B43: 17.751843 | C43: 16.584767 | D43: 18.673219 | E43: 24.447174 | F43: 22.542998
A44: Diferencia | B44: -11.916462 | C44: -11.855037 | D44: 0 | E44: 11.855037 | F44: 11.916462
A46: A3 | B46: 1 | C46: 2 | D46: 3 | E46: 4 | F46: 5 | G46: SUMA | H46: MEDIA | I46: DT | J46: %_PESO
A47: 1 | B47: 3.16 | C47: -0.27 | D47: 0 | E47: -0.71 | F47: -3.21 | G47: -1.03 | H47: -0.206 | I47: 2.2723622 | J47: 6.2198068
A48: 2 | B48: -0.27 | C48: 0 | D48: 3.16 | E48: -3.02 | F48: -0.71 | G48: -0.84 | H48: -0.168 | I48: 2.2103099 | J48: 5.0724638
A49: 3 | B49: 0 | C49: 3.16 | D49: -0.27 | E49: -3.21 | F49: -2.72 | G49: -3.04 | H49: -0.608 | I49: 2.5452249 | J49: 18.357488
A50: 4 | B50: -2.7 | C50: -2.92 | D50: -3.22 | E50: 3.16 | F50: -0.27 | G50: -5.95 | H50: -1.19 | I50: 2.7001296 | J50: 35.929952
A51: 5 | B51: -3.21 | C51: -2.55 | D51: -2.83 | E51: -0.27 | F51: 3.16 | G51: -5.7 | H51: -1.14 | I51: 2.6634564 | J51: 34.42029
A52: T_COL | B52: -3.02 | C52: -2.58 | D52: -3.16 | E52: -4.05 | F52: -3.75 | G52: -16.56
A53: Media_C | B53: -0.604 | C53: -0.516 | D53: -0.632 | E53: -0.81 | F53: -0.75
A54: DT_C | B54: 2.5410883 | C54: 2.4370125 | D54: 2.5709278 | E54: 2.5839214 | F54: 2.5225285
A55: %_PESO | B55: 18.236715 | C55: 15.57971 | D55: 19.082126 | E55: 24.456522 | F55: 22.644928 | G55: 100
A56: DA | B56: 6.2198068 | C56: 5.0724638 | D56: 18.357488 | E56: 35.929952 | F56: 34.42029
A57: Diferencia | B57: 12.016908 | C57: 10.507246 | D57: 0.72463768 | E57: -11.47343 | F57: -11.775362
A59: A4 | B59: 1 | C59: 2 | D59: 3 | E59: 4 | F59: 5 | G59: SUMA | H59: MEDIA | I59: DT | J59: %_PESO
A60: 1 | B60: 4.44 | C60: 1.26 | D60: 0 | E60: -0.71 | F60: -3.2 | G60: 1.79 | H60: 0.358 | I60: 2.801985 | J60: 36.234818
A61: 2 | B61: 1.26 | C61: 0 | D61: 4.44 | E61: -2.69 | F61: -0.71 | G61: 2.3 | H61: 0.46 | I61: 2.6449669 | J61: 46.558704
A62: 3 | B62: 0 | C62: 4.44 | D62: 1.26 | E62: -3.2 | F62: -1.26 | G62: 1.24 | H62: 0.248 | I62: 2.864493 | J62: 25.101215
A63: 4 | B63: -0.63 | C63: -2.86 | D63: -3.21 | E63: 4.44 | F63: 1.26 | G63: -1 | H63: -0.2 | I63: 3.1615582 | J63: -20.242915
A64: 5 | B64: -3.2 | C64: -0.63 | D64: -1.26 | E64: 1.26 | F64: 4.44 | G64: 0.61 | H64: 0.122 | I64: 2.8918541 | J64: 12.348178
A65: T_COL | B65: 1.87 | C65: 2.21 | D65: 1.23 | E65: -0.9 | F65: 0.53 | G65: 4.94
A66: Media_C | B66: 0.374 | C66: 0.442 | D66: 0.246 | E66: -0.18 | F66: 0.106
A67: DT_C | B67: 2.7945805 | C67: 2.6879769 | D67: 2.8675041 | E67: 3.1272752 | F67: 2.8972711
A68: %_PESO | B68: 37.854251 | C68: 44.736842 | D68: 24.898785 | E68: -18.218623 | F68: 10.728745 | G68: 100
A69: DA | B69: 36.234818 | C69: 46.558704 | D69: 25.101215 | E69: -20.242915 | F69: 12.348178
A70: Diferencia | B70: 1.6194332 | C70: -1.8218623 | D70: -0.20242915 | E70: 2.0242915 | F70: -1.6194332
A72: ► 4.03 GRUPO SDA SRC SDR DENSIDAD RELACIONAL DADA: EMITIDA / RECIBIDA / TOTAL VALORATIVA | L72: ► 4.04 RESUMEN DE DENSIDADES
A74: SDA | B74: 1 | C74: 2 | D74: 3 | E74: 4 | F74: 5 | G74: SUMA | H74: MEDIA | I74: DT | J74: %_PESO | L74: RESUMEN | M74: SUMA | N74: MEDIA | O74: DT | P74: %_PESO
A75: 1 | B75: 7.6 | C75: 0.99 | D75: 0 | E75: -3.28 | F75: -6.41 | G75: -1.1 | H75: -0.22 | I75: 5.2522519 | J75: 9.8214286 | L75: SDA | M75: -11.2 | N75: -0.448 | O75: 4.79716 | P75: -24.539877
A76: 2 | B76: 0.99 | C76: 0 | D76: 7.6 | E76: -5.99 | F76: -3.28 | G76: -0.68 | H76: -0.136 | I76: 5.1304512 | J76: 6.0714286 | L76: SRC | M76: -11.62 | N76: -0.4648 | O76: 4.803015 | P76: -25.460123
A77: 3 | B77: 0 | C77: 7.6 | D77: 0.99 | E77: -6.41 | F77: -3.98 | G77: -1.8 | H77: -0.36 | I77: 5.3623829 | J77: 16.071429 | L77: SDR | M77: -22.82 | N77: -0.9128 | O77: 9.5687418 | P77: -50
A78: 4 | B78: -1.26 | C78: -5.48 | D78: -6.41 | E78: 7.6 | F78: 0.99 | G78: -4.56 | H78: -0.912 | I78: 5.6410877 | J78: 40.714286
A79: 5 | B79: -6.41 | C79: -1.26 | D79: -3.98 | E79: 0.99 | F79: 7.6 | G79: -3.06 | H79: -0.612 | I79: 5.3708351 | J79: 27.321429
A80: T_COL | B80: 0.92 | C80: 1.85 | D80: -1.8 | E80: -7.09 | F80: -5.08 | G80: -11.2
A81: Media_C | B81: 0.184 | C81: 0.37 | D81: -0.36 | E81: -1.418 | F81: -1.016
A82: DT_C | B82: 5.0310665 | C82: 4.7348073 | D82: 5.3623829 | E82: 5.8398005 | F82: 5.5060358
A83: %_PESO | B83: -8.2142857 | C83: -16.517857 | D83: 16.071429 | E83: 63.303571 | F83: 45.357143 | G83: 100
A84: DA | B84: 9.8214286 | C84: 6.0714286 | D84: 16.071429 | E84: 40.714286 | F84: 27.321429
A85: Diferencia | B85: -18.035714 | C85: -22.589286 | D85: 0 | E85: 22.589286 | F85: 18.035714
A87: SRC | B87: 1 | C87: 2 | D87: 3 | E87: 4 | F87: 5 | G87: SUMA | H87: MEDIA | I87: DT | J87: %_PESO
A88: 1 | B88: 7.6 | C88: 0.99 | D88: 0 | E88: -1.42 | F88: -6.41 | G88: 0.76 | H88: 0.152 | I88: 5.0430417 | J88: -6.5404475
A89: 2 | B89: 0.99 | C89: 0 | D89: 7.6 | E89: -5.71 | F89: -1.42 | G89: 1.46 | H89: 0.292 | I89: 4.8201214 | J89: -12.564544
A90: 3 | B90: 0 | C90: 7.6 | D90: 0.99 | E90: -6.41 | F90: -3.98 | G90: -1.8 | H90: -0.36 | I90: 5.3623829 | J90: 15.490534
A91: 4 | B91: -3.33 | C91: -5.78 | D91: -6.43 | E91: 7.6 | F91: 0.99 | G91: -6.95 | H91: -1.39 | I91: 5.8077922 | J91: 59.810671
A92: 5 | B92: -6.41 | C92: -3.18 | D92: -4.09 | E92: 0.99 | F92: 7.6 | G92: -5.09 | H92: -1.018 | I92: 5.5110589 | J92: 43.803787
A93: T_COL | B93: -1.15 | C93: -0.37 | D93: -1.93 | E93: -4.95 | F93: -3.22 | G93: -11.62
A94: Media_C | B94: -0.23 | C94: -0.074 | D94: -0.386 | E94: -0.99 | F94: -0.644
A95: DT_C | B95: 5.259577 | C95: 5.0555296 | D95: 5.3867458 | E95: 5.6909621 | F95: 5.3761352
A96: %_PESO | B96: 9.8967298 | C96: 3.1841652 | D96: 16.609294 | E96: 42.598967 | F96: 27.710843 | G96: 100
A97: DA | B97: -6.5404475 | C97: -12.564544 | D97: 15.490534 | E97: 59.810671 | F97: 43.803787
A98: Diferencia | B98: 16.437177 | C98: 15.748709 | D98: 1.1187608 | E98: -17.211704 | F98: -16.092943
A100: SDR | B100: 1 | C100: 2 | D100: 3 | E100: 4 | F100: 5 | G100: SUMA | H100: MEDIA | I100: DT | J100: %_PESO
A101: 1 | B101: 15.2 | C101: 1.98 | D101: 0 | E101: -4.7 | F101: -12.82 | G101: -0.34 | H101: -0.068 | I101: 10.263767 | J101: 1.4899211
A102: 2 | B102: 1.98 | C102: 0 | D102: 15.2 | E102: -11.7 | F102: -4.7 | G102: 0.78 | H102: 0.156 | I102: 9.9224332 | J102: -3.4180543
A103: 3 | B103: 0 | C103: 15.2 | D103: 1.98 | E103: -12.82 | F103: -7.96 | G103: -3.6 | H103: -0.72 | I103: 10.724766 | J103: 15.775635
A104: 4 | B104: -4.59 | C104: -11.26 | D104: -12.84 | E104: 15.2 | F104: 1.98 | G104: -11.51 | H104: -2.302 | I104: 11.414746 | J104: 50.438212
A105: 5 | B105: -12.82 | C105: -4.44 | D105: -8.07 | E105: 1.98 | F105: 15.2 | G105: -8.15 | H105: -1.63 | I105: 10.849733 | J105: 35.714286
A106: T_COL | B106: -0.23 | C106: 1.48 | D106: -3.73 | E106: -12.04 | F106: -8.3 | G106: -22.82
A107: Media_C | B107: -0.046 | C107: 0.296 | D107: -0.746 | E107: -2.408 | F107: -1.66 | H107: =AVERAGE(B101:F105) -> -0.9128
A108: DT_C | B108: 10.251467 | C108: 9.7599119 | D108: 10.74905 | E108: 11.503266 | F108: 10.851111
A109: %_PESO | B109: 1.0078878 | C109: -6.485539 | D109: 16.345311 | E109: 52.760736 | F109: 36.371604 | G109: 100
A110: DA | B110: 1.4899211 | C110: -3.4180543 | D110: 15.775635 | E110: 50.438212 | F110: 35.714286
A111: Diferencia | B111: -0.4820333 | C111: -3.0674847 | D111: 0.56967572 | E111: 2.3225241 | F111: 0.65731814
...

Sheet 5.PRISMAS
C1: 1G1T1C PRISMAS RELACIONALES Y MATRICES DE DIFRACCIÓN 9x9
G2: Matriz ID: | H2: 1g1t1c (G2-T1-C1)
G3: Etapa: | H3: T1 - Diagnóstico Base | K3: Proyecto: | L3: Dossier Analítico NEX_ORD
C4: SIMULACIÓN IN SILICO Datos Anonimizados | G4: Motor Core: | H4: NEX_ORD Platinum v6.0 | K4: Analizado: | L4: 260829_154156
G5: Path Audit: | H5: .../05_Output/FULL_TABLES_1g1t1c.xlsx | K5: Protocolo: | L5: DOI 10.5281/zenodo.189416.1
A7: ► 5.01 MATRIZ DE DIFRACCIÓN NETA 1 (9x9): ASIMETRÍA DE FLUIDO NETO (SRC - SDA)
A8: Figura / Eje | B8: <Ee> | C8: <Ee! | D8: <Ee] | E8: <E?> | F8: <E?! | G8: <E?] | H8: <Er> | I8: <Er! | J8: <Er]
A9: <Ee> | B9: -0.01 | C9: 0.146 | D9: -0.166 | E9: -0.77 | F9: -0.424 | G9: -0.01 | H9: 0.146 | I9: -0.166 | J9: -0.77
A10: <Ee! | B10: -0.094 | C10: 0.062 | D10: -0.25 | E10: -0.854 | F10: -0.508 | G10: -0.094 | H10: 0.062 | I10: -0.25 | J10: -0.854
A11: <Ee] | B11: 0.13 | C11: 0.286 | D11: -0.026 | E11: -0.63 | F11: -0.284 | G11: 0.13 | H11: 0.286 | I11: -0.026 | J11: -0.63
A12: <E?> | B12: 0.682 | C12: 0.838 | D12: 0.526 | E12: -0.078 | F12: 0.268 | G12: 0.682 | H12: 0.838 | I12: 0.526 | J12: -0.078
A13: <E?! | B13: 0.382 | C13: 0.538 | D13: 0.226 | E13: -0.378 | F13: -0.032 | G13: 0.382 | H13: 0.538 | I13: 0.226 | J13: -0.378
A14: <E?] | B14: -0.01 | C14: 0.146 | D14: -0.166 | E14: -0.77 | F14: -0.424 | G14: -0.01 | H14: 0.146 | I14: -0.166 | J14: -0.77
A15: <Er> | B15: -0.094 | C15: 0.062 | D15: -0.25 | E15: -0.854 | F15: -0.508 | G15: -0.094 | H15: 0.062 | I15: -0.25 | J15: -0.854
A16: <Er! | B16: 0.13 | C16: 0.286 | D16: -0.026 | E16: -0.63 | F16: -0.284 | G16: 0.13 | H16: 0.286 | I16: -0.026 | J16: -0.63
A17: <Er] | B17: 0.682 | C17: 0.838 | D17: 0.526 | E17: -0.078 | F17: 0.268 | G17: 0.682 | H17: 0.838 | I17: 0.526 | J17: -0.078
A20: ► 5.02 MATRIZ DE DIFRACCIÓN BRUTA 2 (9x9): ASIMETRÍA DE FLUIDO BRUTO (BRC - BDA)
A21: Figura / Eje | B21: <Ee> | C21: <Ee! | D21: <Ee] | E21: <E?> | F21: <E?! | G21: <E?] | H21: <Er> | I21: <Er! | J21: <Er]
A22: <Ee> | B22: 0.01 | C22: -0.146 | D22: 0.166 | E22: 0.77 | F22: 0.424 | G22: 0.01 | H22: -0.146 | I22: 0.166 | J22: 0.77
A23: <Ee! | B23: 0.094 | C23: -0.062 | D23: 0.25 | E23: 0.854 | F23: 0.508 | G23: 0.094 | H23: -0.062 | I23: 0.25 | J23: 0.854
A24: <Ee] | B24: -0.13 | C24: -0.286 | D24: 0.026 | E24: 0.63 | F24: 0.284 | G24: -0.13 | H24: -0.286 | I24: 0.026 | J24: 0.63
A25: <E?> | B25: -0.682 | C25: -0.838 | D25: -0.526 | E25: 0.078 | F25: -0.268 | G25: -0.682 | H25: -0.838 | I25: -0.526 | J25: 0.078
A26: <E?! | B26: -0.382 | C26: -0.538 | D26: -0.226 | E26: 0.378 | F26: 0.032 | G26: -0.382 | H26: -0.538 | I26: -0.226 | J26: 0.378
A27: <E?] | B27: 0.01 | C27: -0.146 | D27: 0.166 | E27: 0.77 | F27: 0.424 | G27: 0.01 | H27: -0.146 | I27: 0.166 | J27: 0.77
A28: <Er> | B28: 0.094 | C28: -0.062 | D28: 0.25 | E28: 0.854 | F28: 0.508 | G28: 0.094 | H28: -0.062 | I28: 0.25 | J28: 0.854
A29: <Er! | B29: -0.13 | C29: -0.286 | D29: 0.026 | E29: 0.63 | F29: 0.284 | G29: -0.13 | H29: -0.286 | I29: 0.026 | J29: 0.63
A30: <Er] | B30: -0.682 | C30: -0.838 | D30: -0.526 | E30: 0.078 | F30: -0.268 | G30: -0.682 | H30: -0.838 | I30: -0.526 | J30: 0.078
A33: ► 5.03 MATRIZ DE DIFRACCIÓN DE EXPECTATIVAS 3 (9x9): DESCALCE DE SINTONÍA (A4 - A1)
A34: Figura / Eje | B34: <Ee> | C34: <Ee! | D34: <Ee] | E34: <E?> | F34: <E?! | G34: <E?] | H34: <Er> | I34: <Er! | J34: <Er]
A35: <Ee> | B35: 0.016 | C35: 0.084 | D35: -0.112 | E35: -0.538 | F35: -0.252 | G35: 0.016 | H35: 0.084 | I35: -0.112 | J35: -0.538
A36: <Ee! | B36: -0.03 | C36: 0.038 | D36: -0.158 | E36: -0.584 | F36: -0.298 | G36: -0.03 | H36: 0.038 | I36: -0.158 | J36: -0.584
A37: <Ee] | B37: 0.126 | C37: 0.194 | D37: -0.002 | E37: -0.428 | F37: -0.142 | G37: 0.126 | H37: 0.194 | I37: -0.002 | J37: -0.428
A38: <E?> | B38: 0.49 | C38: 0.558 | D38: 0.362 | E38: -0.064 | F38: 0.222 | G38: 0.49 | H38: 0.558 | I38: 0.362 | J38: -0.064
A39: <E?! | B39: 0.252 | C39: 0.32 | D39: 0.124 | E39: -0.302 | F39: -0.016 | G39: 0.252 | H39: 0.32 | I39: 0.124 | J39: -0.302
A40: <E?] | B40: 0.016 | C40: 0.084 | D40: -0.112 | E40: -0.538 | F40: -0.252 | G40: 0.016 | H40: 0.084 | I40: -0.112 | J40: -0.538
A41: <Er> | B41: -0.03 | C41: 0.038 | D41: -0.158 | E41: -0.584 | F41: -0.298 | G41: -0.03 | H41: 0.038 | I41: -0.158 | J41: -0.584
A42: <Er! | B42: 0.126 | C42: 0.194 | D42: -0.002 | E42: -0.428 | F42: -0.142 | G42: 0.126 | H42: 0.194 | I42: -0.002 | J42: -0.428
A43: <Er] | B43: 0.49 | C43: 0.558 | D43: 0.362 | E43: -0.064 | F43: 0.222 | G43: 0.49 | H43: 0.558 | I43: 0.362 | J43: -0.064
A46: ► 5.04 PRISMA INDIVIDUAL 1 (N x 9) | P46: ► 5.10 RESUMEN SÍNTESIS DE PRISMAS TOTALES
A48: PRISMA1 | B48: <E.. | C48: <¿.. | D48: <R.. | E48: ¡E.. | F48: ¡¿.. | G48: ¡R.. | H48: [E.. | I48: [¿.. | J48: [R.. | K48: SUMA | L48: MEDIA | M48: DT | N48: %_PESO | P48: RESUMEN | Q48: SUMA | R48: MEDIA | S48: DT | T48: %_PESO
A49: 1 | B49: 30.4 | E49: 6.12 | F49: 4.59 | G49: 4.7 | J49: 25.62 | K49: 180.36 | L49: 22.25 | M49: 48.35 | N49: 17.94 | P49: PRISMA1 | Q49: 1005.31 | R49: 15.466308 | S49: 21.544178 | T49: 17.232773
A50: 2 | B50: 30.4 | E50: 6.12 | F50: 4.45 | G50: 15.96 | J50: 11.69 | K50: 172.33 | L50: 21.23 | M50: 46.07 | N50: 17.14 | P50: PRISMA2 | Q50: 1005.16 | R50: 15.464 | S50: 21.533393 | T50: 17.230202
A51: 3 | B51: 30.4 | E51: 6.12 | G51: 16.03 | J51: 25.65 | K51: 196.87 | L51: 24.27 | M51: 52.7 | N51: 19.58 | P51: PRISMA3 | Q51: 1005.22 | R51: 15.464923 | S51: 21.538581 | T51: 17.23123
A52: 4 | B52: 30.4 | E52: 6.12 | F52: 4.59 | G52: 15.96 | J52: 37.34 | K52: 237.23 | L52: 29.23 | M52: 63.44 | N52: 23.6 | P52: PRISMA4 | Q52: 1005.25 | R52: 15.465385 | S52: 21.539104 | T52: 17.231744
A53: 5 | B53: 30.4 | E53: 6.12 | F53: 4.45 | G53: 20.73 | J53: 25.62 | K53: 218.52 | L53: 26.9 | M53: 58.32 | N53: 21.74 | P53: PRISMA5 | Q53: 1007.02 | R53: 15.492615 | S53: 21.665447 | T53: 17.262085
A54: SUMA | B54: 152 | C54: 0 | D54: 0 | E54: 30.6 | F54: 18.08 | G54: 73.38 | H54: 0 | I54: 0 | J54: 125.92 | K54: 1005.31 | L54: 123.9 | M54: 268.87 | N54: 100 | P54: PRISMA6 | Q54: 805.75 | R54: 12.396154 | S54: 18.424482 | T54: 13.811965
A55: MEDIA | B55: 30.4 | C55: 0 | D55: 0 | E55: 6.12 | F55: 3.62 | G55: 14.68 | H55: 0 | I55: 0 | J55: 25.18 | K55: 201.06 | L55: 24.78 | M55: 53.77 | N55: 20
A56: DT | B56: 0 | C56: 0 | D56: 0 | E56: 0 | F56: 2.02 | G56: 5.94 | H56: 0 | I56: 0 | J56: 9.09 | K56: 26.85 | L56: 3.3 | M56: 7.14 | N56: 2.67
A57: %_PESO | B57: 15.12 | C57: 0 | D57: 0 | E57: 3.04 | F57: 1.8 | G57: 7.3 | H57: 0 | I57: 0 | J57: 12.53 | K57: 100 | L57: 12.32 | M57: 26.75 | N57: 100
A60: ► 5.05 PRISMA INDIVIDUAL 2 (N x 9)
A62: PRISMA2 | B62: ..e> | C62: ..?> | D62: ..r> | E62: ..e! | F62: ..?! | G62: ..r! | H62: ..e] | I62: ..?] | J62: ..r] | K62: SUMA | L62: MEDIA | M62: DT | N62: %_PESO
A63: 1 | B63: 30.4 | E63: 6.12 | F63: 4.7 | G63: 4.59 | J63: 25.62 | K63: 180.36 | L63: 22.25 | M63: 48.35 | N63: 17.94
A64: 2 | B64: 30.4 | E64: 6.12 | F64: 4.7 | G64: 16.14 | J64: 11.26 | K64: 172.31 | L64: 21.23 | M64: 46.06 | N64: 17.14
A65: 3 | B65: 30.4 | E65: 6.12 | G65: 16.03 | J65: 25.65 | K65: 196.87 | L65: 24.27 | M65: 52.7 | N65: 19.59
A66: 4 | B66: 30.4 | E66: 6.12 | F66: 4.7 | G66: 16.28 | J66: 36.91 | K66: 237.14 | L66: 29.22 | M66: 63.4 | N66: 23.59
A67: 5 | B67: 30.4 | E67: 6.12 | F67: 4.7 | G67: 20.48 | J67: 25.62 | K67: 218.48 | L67: 26.9 | M67: 58.3 | N67: 21.74
A68: SUMA | B68: 152 | C68: 0 | D68: 0 | E68: 30.6 | F68: 18.8 | G68: 73.52 | H68: 0 | I68: 0 | J68: 125.06 | K68: 1005.16 | L68: 123.87 | M68: 268.81 | N68: 100
A69: MEDIA | B69: 30.4 | C69: 0 | D69: 0 | E69: 6.12 | F69: 3.76 | G69: 14.7 | H69: 0 | I69: 0 | J69: 25.01 | K69: 201.03 | L69: 24.77 | M69: 53.76 | N69: 20
A70: DT | B70: 0 | C70: 0 | D70: 0 | E70: 0 | F70: 2.1 | G70: 5.96 | H70: 0 | I70: 0 | J70: 9.11 | K70: 26.82 | L70: 3.3 | M70: 7.13 | N70: 2.67
A71: %_PESO | B71: 15.12 | C71: 0 | D71: 0 | E71: 3.04 | F71: 1.87 | G71: 7.31 | H71: 0 | I71: 0 | J71: 12.44 | K71: 100 | L71: 12.32 | M71: 26.74 | N71: 100
A74: ► 5.06 PRISMA INDIVIDUAL 3 (N x 9)
A76: PRISMA3 | B76: <.e. | C76: <.?. | D76: <.r. | E76: ¡.e. | F76: ¡.?. | G76: ¡.r. | H76: [.e. | I76: [.?. | J76: [.r. | K76: SUMA | L76: MEDIA | M76: DT | N76: %_PESO
A77: 1 | B77: 30.4 | E77: 6.12 | F77: 4.7 | G77: 4.59 | J77: 25.62 | K77: 180.36 | L77: 22.25 | M77: 48.35 | N77: 17.94
A78: 2 | B78: 30.4 | E78: 6.12 | F78: 4.7 | G78: 15.71 | J78: 11.69 | K78: 172.29 | L78: 21.23 | M78: 46.05 | N78: 17.14
A79: 3 | B79: 30.4 | E79: 6.12 | G79: 16.03 | J79: 25.65 | K79: 196.87 | L79: 24.27 | M79: 52.7 | N79: 19.58
A80: 4 | B80: 30.4 | E80: 6.12 | F80: 4.7 | G80: 15.85 | J80: 37.34 | K80: 237.22 | L80: 29.23 | M80: 63.43 | N80: 23.6
A81: 5 | B81: 30.4 | E81: 6.12 | F81: 4.7 | G81: 20.48 | J81: 25.62 | K81: 218.48 | L81: 26.9 | M81: 58.3 | N81: 21.73
A82: SUMA | B82: 152 | C82: 0 | D82: 0 | E82: 30.6 | F82: 18.8 | G82: 72.66 | H82: 0 | I82: 0 | J82: 125.92 | K82: 1005.22 | L82: 123.88 | M82: 268.84 | N82: 100
A83: MEDIA | B83: 30.4 | C83: 0 | D83: 0 | E83: 6.12 | F83: 3.76 | G83: 14.53 | H83: 0 | I83: 0 | J83: 25.18 | K83: 201.04 | L83: 24.78 | M83: 53.77 | N83: 20
A84: DT | B84: 0 | C84: 0 | D84: 0 | E84: 0 | F84: 2.1 | G84: 5.91 | H84: 0 | I84: 0 | J84: 9.09 | K84: 26.85 | L84: 3.3 | M84: 7.14 | N84: 2.67
A85: %_PESO | B85: 15.12 | C85: 0 | D85: 0 | E85: 3.04 | F85: 1.87 | G85: 7.23 | H85: 0 | I85: 0 | J85: 12.53 | K85: 100 | L85: 12.32 | M85: 26.74 | N85: 100
A88: ► 5.07 PRISMA INDIVIDUAL 4 (N x 9)
A90: PRISMA4 | B90: .E.> | C90: .¿.> | D90: .R.> | E90: .E.! | F90: .¿.! | G90: .R.! | H90: .E.] | I90: .¿.] | J90: .R.] | K90: SUMA | L90: MEDIA | M90: DT | N90: %_PESO
A91: 1 | B91: 30.4 | E91: 6.12 | F91: 4.59 | G91: 4.7 | J91: 25.62 | K91: 180.36 | L91: 22.25 | M91: 48.35 | N91: 17.94
A92: 2 | B92: 30.4 | E92: 6.12 | F92: 4.45 | G92: 16.39 | J92: 11.26 | K92: 172.35 | L92: 21.24 | M92: 46.08 | N92: 17.14
A93: 3 | B93: 30.4 | E93: 6.12 | G93: 16.03 | J93: 25.65 | K93: 196.87 | L93: 24.27 | M93: 52.7 | N93: 19.58
A94: 4 | B94: 30.4 | E94: 6.12 | F94: 4.59 | G94: 16.39 | J94: 36.91 | K94: 237.15 | L94: 29.22 | M94: 63.41 | N94: 23.59
A95: 5 | B95: 30.4 | E95: 6.12 | F95: 4.45 | G95: 20.73 | J95: 25.62 | K95: 218.52 | L95: 26.9 | M95: 58.32 | N95: 21.74
A96: SUMA | B96: 152 | C96: 0 | D96: 0 | E96: 30.6 | F96: 18.08 | G96: 74.24 | H96: 0 | I96: 0 | J96: 125.06 | K96: 1005.25 | L96: 123.89 | M96: 268.85 | N96: 100
A97: MEDIA | B97: 30.4 | C97: 0 | D97: 0 | E97: 6.12 | F97: 3.62 | G97: 14.85 | H97: 0 | I97: 0 | J97: 25.01 | K97: 201.05 | L97: 24.78 | M97: 53.77 | N97: 20
A98: DT | B98: 0 | C98: 0 | D98: 0 | E98: 0 | F98: 2.02 | G98: 5.99 | H98: 0 | I98: 0 | J98: 9.11 | K98: 26.82 | L98: 3.3 | M98: 7.13 | N98: 2.67
A99: %_PESO | B99: 15.12 | C99: 0 | D99: 0 | E99: 3.04 | F99: 1.8 | G99: 7.39 | H99: 0 | I99: 0 | J99: 12.44 | K99: 100 | L99: 12.32 | M99: 26.74 | N99: 100
A102: ► 5.08 PRISMA INDIVIDUAL 5 (N x 9)
A104: PRISMA5 | B104: <..> | C104: <..! | D104: <..] | E104: ¡..> | F104: ¡..! | G104: ¡..] | H104: [..> | I104: [..! | J104: [..] | K104: SUMA | L104: MEDIA | M104: DT | N104: %_PESO
A105: 1 | B105: 30.4 | F105: 15.41 | J105: 25.62 | K105: 181.17 | L105: 22.38 | M105: 48.69 | N105: 17.99
A106: 2 | B106: 30.4 | F106: 15.27 | G106: 11.26 | I106: 11.69 | K106: 172.61 | L106: 21.28 | M106: 46.18 | N106: 17.14
A107: 3 | B107: 30.4 | F107: 22.15 | J107: 25.65 | K107: 197.84 | L107: 24.42 | M107: 53.09 | N107: 19.65
A108: 4 | B108: 30.4 | F108: 15.41 | G108: 11.26 | I108: 11.69 | J108: 25.65 | K108: 234.6 | L108: 28.83 | M108: 62.42 | N108: 23.3
A109: 5 | B109: 30.4 | F109: 31.3 | J109: 25.62 | K109: 220.8 | L109: 27.25 | M109: 59.24 | N109: 21.93
A110: SUMA | B110: 152 | C110: 0 | D110: 0 | E110: 0 | F110: 99.54 | G110: 22.52 | H110: 0 | I110: 23.38 | J110: 102.54 | K110: 1007.02 | L110: 124.16 | M110: 269.62 | N110: 100
A111: MEDIA | B111: 30.4 | C111: 0 | D111: 0 | E111: 0 | F111: 19.91 | G111: 4.5 | H111: 0 | I111: 4.68 | J111: 20.51 | K111: 201.4 | L111: 24.83 | M111: 53.92 | N111: 20
A112: DT | B112: 0 | C112: 0 | D112: 0 | E112: 0 | F112: 7.01 | G112: 6.17 | H112: 0 | I112: 6.4 | J112: 11.46 | K112: 26.12 | L112: 3.19 | M112: 6.86 | N112: 2.59
A113: %_PESO | B113: 15.09 | C113: 0 | D113: 0 | E113: 0 | F113: 9.88 | G113: 2.24 | H113: 0 | I113: 2.32 | J113: 10.18 | K113: 100 | L113: 12.33 | M113: 26.77 | N113: 100
A116: ► 5.09 PRISMA INDIVIDUAL 6 (N x 9)
A118: PRISMA6 | B118: .Ee. | C118: .E?. | D118: .Er. | E118: .¿e. | F118: .¿?. | G118: .¿r. | H118: .Re. | I118: .R?. | J118: .Rr. | K118: SUMA | L118: MEDIA | M118: DT | N118: %_PESO
A119: 1 | B119: 6.12 | G119: 4.59 | I119: 4.7 | J119: 25.62 | K119: 108.47 | L119: 13.53 | M119: 29.31 | N119: 13.46
A120: 2 | B120: 36.52 | G120: 4.45 | I120: 4.7 | J120: 22.95 | K120: 180.66 | L120: 22.52 | M120: 48.7 | N120: 22.42
A121: 3 | B121: 30.4 | J121: 41.68 | K121: 192.13 | L121: 24.01 | M121: 52.2 | N121: 23.84
A122: 4 | B122: 6.12 | G122: 4.59 | I122: 4.7 | J122: 48.6 | K122: 172.04 | L122: 21.54 | M122: 47.02 | N122: 21.35
A123: 5 | B123: 6.12 | G123: 4.45 | I123: 4.7 | J123: 41.65 | K123: 152.45 | L123: 19.08 | M123: 41.56 | N123: 18.92
...

Sheet 6.Reciprocidad
C1: 1G1T1C RECIPROCIDAD DE FIGURAS RELACIONALES MÚTUAS
G2: Matriz ID: | H2: 1g1t1c (G2-T1-C1)
G3: Etapa: | H3: T1 - Diagnóstico Base | K3: Proyecto: | L3: Dossier Analítico NEX_ORD
C4: SIMULACIÓN IN SILICO Datos Anonimizados | G4: Motor Core: | H4: NEX_ORD Platinum v6.0 | K4: Analizado: | L4: 260829_154156
G5: Path Audit: | H5: .../05_Output/FULL_TABLES_1g1t1c.xlsx | K5: Protocolo: | L5: DOI 10.5281/zenodo.189416.1
A8: ► 6.00 RESUMEN SÍNTESIS DE VALENCIAS MÚTUAS Y CALIBRACIÓN DE DENSIDAD SDR
A9: Métrica / Valencia Mútua | B9: Símbolo Canónico | C9: Conteo / Valor Promedio | D9: % Total / Calibración
A10: Reciprocidad Positiva (Afinidad Mútua) | B10: Ee | C10: 0 | D10: 0
A11: Reciprocidad Neutra (Indiferencia Mútua) | B11: ¿? | C11: 0 | D11: 0
A12: Reciprocidad Negativa (Rechazo Mútuo) | B12: Rr | C12: 0 | D12: 0
A13: Centroide SDR (Masa Total de Figuras Recíprocas) | B13: μ_SDR | C13: -0.9128 | D13: 100
A16: ► 6.01 SÍNTESIS DE RECIPROCIDAD Y CENTROIDE SDR POR SUJETO
A17: ID_Sujeto | B17: Centroide SDR (Sujeto) | C17: Mútuos Positivos Ee (%) | D17: Mútuos Neutros ¿? (%) | E17: Mútuos Negativos Rr (%) | F17: Total Reciprocidad (%)
A18: 1 | B18: -0.068 | C18: 0 | D18: 0 | E18: 0 | F18: 0
A19: 2 | B19: 0.156 | C19: 0 | D19: 0 | E19: 0 | F19: 0
A20: 3 | B20: -0.72 | C20: 0 | D20: 0 | E20: 0 | F20: 0
A21: 4 | B21: -2.302 | C21: 0 | D21: 0 | E21: 0 | F21: 0
A22: 5 | B22: -1.63 | C22: 0 | D22: 0 | E22: 0 | F22: 0
A23: Media | B23: =AVERAGE(B18:B22) -> 0 | C23: =AVERAGE(C18:C22) -> 0 | D23: =AVERAGE(D18:D22) -> 0 | E23: =AVERAGE(E18:E22) -> 0 | F23: =AVERAGE(F18:F22) -> 0

Sheet 7.Variables
C1: 1G1T1C ► 7.01 CENTROIDES DE DENSIDAD POR MODALIDAD
G2: Matriz ID: | H2: 1g1t1c (G2-T1-C1)
G3: Etapa: | H3: T1 - Diagnóstico Base | K3: Proyecto: | L3: Dossier Analítico NEX_ORD
C4: SIMULACIÓN IN SILICO Datos Anonimizados | G4: Motor Core: | H4: NEX_ORD Platinum v6.0 | K4: Analizado: | L4: 260829_154156
G5: Path Audit: | H5: .../05_Output/FULL_TABLES_1g1t1c.xlsx | K5: Protocolo: | L5: DOI 10.5281/zenodo.189416.1
A7: ► 7.01 VARIABLES COMPLEMENTARIAS | P7: ► 7.02 DESCRIPCION DE VARIABLES COMPLEMENTARIAS
A9: VARIABLE | B9: Modalidad | C9: n_sujetos | D9: A1 | E9: A2 | F9: A3 | G9: A4 | H9: SDA | I9: SRC | J9: SDR | K9: BDA | L9: BRC | M9: BDR | N9: SINTONIA | P9: VAR | Q9: NOM | R9: N_mod | S9: 1 | T9: 2 | U9: 3
A12: ► 7.04 HISTOGRAMA DE DISTRIBUCION DE LAS VARIABLES COMPLEMENTARIAS EN EL GRUPO TOTAL
A13: Modalidad | B13: MIN | C13: VAL | D13: MAX
P15: VAR_
A16: ► 7.05 GRAFICA DE DISPERSION DE CENTROIDES DE LAS MODALIDADES EN EL GRUPO TOTAL | P16: 1
P17: 2
P18: 3
P19: 4
P20: 5

Sheet 8.AAG_D
C1: 1G1T1C ► 8.01 DISTRIBUCION DE ADJETIVOS (AAG)
G2: Matriz ID: | H2: 1g1t1c (G2-T1-C1)
G3: Etapa: | H3: T1 - Diagnóstico Base | K3: Proyecto: | L3: Dossier Analítico NEX_ORD
C4: SIMULACIÓN IN SILICO Datos Anonimizados | G4: Motor Core: | H4: NEX_ORD Platinum v6.0 | K4: Analizado: | L4: 260829_154156
G5: Path Audit: | H5: .../05_Output/FULL_TABLES_1g1t1c.xlsx | K5: Protocolo: | L5: DOI 10.5281/zenodo.189416.1
A7: ► 8.01 AAG DICOTOMICA DENSIDAD RELACIONAL
A9: Categoría | B9: + / - | C9: sujetos | D9: Valor Adjetivo | E9: A1 | F9: A2 | G9: A3 | H9: A4 | I9: SDA | J9: SRC | K9: SDR | L9: BDA | M9: BRC | N9: BDR | O9: SINTONIA
A10: +sx | B10: + | C10: 3 | E10: 0.24266667 | F10: -0.64 | G10: -0.65666667 | H10: 0.24233333 | I10: -0.39533333 | J10: -0.41233333 | K10: -0.81166667 | L10: 3.9413333 | M10: 3.9583333 | N10: 7.8996667 | O10: 1.6402593
A11: -sx | B11: - | C11: 2 | E11: 0.144 | F11: -0.668 | G11: -0.671 | H11: 0.1305 | I11: -0.522 | J11: -0.5375 | K11: -1.0645 | L11: 4.068 | M11: 4.0845 | N11: 8.1525 | O11: 1.6800556
A12: +ed | B12: + | C12: 2 | E12: -0.031 | F12: -0.9585 | G12: -0.9725 | H12: -0.038 | I12: -0.9875 | J12: -1.008 | K12: -2 | L12: 4.5335 | M12: 4.5545 | N12: 9.088 | O12: 1.8932222
A13: -ed | B13: - | C13: 3 | E13: 0.35933333 | F13: -0.44633333 | G13: -0.45566667 | H13: 0.35466667 | I13: -0.085 | J13: -0.098666667 | K13: -0.188 | L13: 3.631 | M13: 3.645 | N13: 7.276 | O13: 1.4981481
A14: +ec | B14: + | C14: 2 | E14: 0.095 | F14: -0.6865 | G14: -0.7025 | H14: 0.088 | I14: -0.5895 | J14: -0.612 | K14: -1.206 | L14: 4.1355 | M14: 4.1585 | N14: 8.294 | O14: 1.6925
A15: -ec | B15: - | C15: 3 | E15: 0.27533333 | F15: -0.62766667 | G15: -0.63566667 | H15: 0.27066667 | I15: -0.35033333 | J15: -0.36266667 | K15: -0.71733333 | L15: 3.8963333 | M15: 3.909 | N15: 7.8053333 | O15: 1.631963
A16: +edu | B16: + | C16: 2 | E16: 0.144 | F16: -0.668 | G16: -0.671 | H16: 0.1305 | I16: -0.522 | J16: -0.5375 | K16: -1.0645 | L16: 4.068 | M16: 4.0845 | N16: 8.1525 | O16: 1.6800556
A17: -edu | B17: - | C17: 3 | E17: 0.24266667 | F17: -0.64 | G17: -0.65666667 | H17: 0.24233333 | I17: -0.39533333 | J17: -0.41233333 | K17: -0.81166667 | L17: 3.9413333 | M17: 3.9583333 | N17: 7.8996667 | O17: 1.6402593
A18: +eco | B18: + | C18: 3 | E18: 0.27533333 | F18: -0.62766667 | G18: -0.63566667 | H18: 0.27066667 | I18: -0.35033333 | J18: -0.36266667 | K18: -0.71733333 | L18: 3.8963333 | M18: 3.909 | N18: 7.8053333 | O18: 1.631963
A19: -eco | B19: - | C19: 2 | E19: 0.095 | F19: -0.6865 | G19: -0.7025 | H19: 0.088 | I19: -0.5895 | J19: -0.612 | K19: -1.206 | L19: 4.1355 | M19: 4.1585 | N19: 8.294 | O19: 1.6925
A20: +fam | B20: + | C20: 2 | E20: 0.036 | F20: -0.7985 | G20: -0.81 | H20: 0.0285 | I20: -0.7605 | J20: -0.779 | K20: -1.544 | L20: 4.3065 | M20: 4.3255 | N20: 8.632 | O20: 1.796
A21: -fam | B21: - | C21: 3 | E21: 0.31466667 | F21: -0.553 | G21: -0.564 | H21: 0.31033333 | I21: -0.23633333 | J21: -0.25133333 | K21: -0.492 | L21: 3.7823333 | M21: 3.7976667 | N21: 7.58 | O21: 1.562963
A24: ► 8.02 TABLA DE DISTRIBUCION DE ADJETIVOS DEL AAG Y PROMEDIOS
A26: Adjetivo | B26: 1 | C26: 2 | D26: 3 | E26: 4 | F26: 5 | G26: Media | H26: DT
A27: sx | B27: 1 | C27: 0 | D27: 1 | E27: 0 | F27: 1 | G27: 0.6 | H27: 0.54772256
A28: ed | B28: 18 | C28: 19 | D28: 20 | E28: 21 | F28: 22 | G28: 20 | H28: 1.5811388
A29: ec | B29: 1 | C29: 0 | D29: 0 | E29: 1 | F29: 0 | G29: 0.4 | H29: 0.54772256
A30: edu | B30: 0 | C30: 1 | D30: 0 | E30: 1 | F30: 0 | G30: 0.4 | H30: 0.54772256
A31: eco | B31: 2 | C31: 3 | D31: 4 | E31: 2 | F31: 3 | G31: 2.8 | H31: 0.83666003
A32: fam | B32: 1 | C32: 2 | D32: 3 | E32: 4 | F32: 1 | G32: 2.2 | H32: 1.3038405
A35: ► 8.03 HISTOGRAMA DE DISTRIBUCION DE ADJETIVOS DEL AAG
A37: AAG | B37: Media | C37: DT
A38: sx | B38: ='8.AAG_D'!G27 -> 0 | C38: ='8.AAG_D'!H27 -> 0
A39: ed | B39: ='8.AAG_D'!G28 -> 0 | C39: ='8.AAG_D'!H28 -> 0
A40: ec | B40: ='8.AAG_D'!G29 -> 0 | C40: ='8.AAG_D'!H29 -> 0
A41: edu | B41: ='8.AAG_D'!G30 -> 0 | C41: ='8.AAG_D'!H30 -> 0
A42: eco | B42: ='8.AAG_D'!G31 -> 0 | C42: ='8.AAG_D'!H31 -> 0
A43: fam | B43: ='8.AAG_D'!G32 -> 0 | C43: ='8.AAG_D'!H32 -> 0
A47: ► 8.04 GRAFICO DE DISPERSION DE CENTROIDES DEL AAG DICOTOMIZADO EN SDA SRC
A49: +sx | B49: -0.39533333 | C49: -0.41233333
A50: -sx | B50: -0.522 | C50: -0.5375
A51: +ed | B51: -0.9875 | C51: -1.008
A52: -ed | B52: -0.085 | C52: -0.098666667
A53: +ec | B53: -0.5895 | C53: -0.612
A54: -ec | B54: -0.35033333 | C54: -0.36266667
A55: +edu | B55: -0.522 | C55: -0.5375
A56: -edu | B56: -0.39533333 | C56: -0.41233333
A57: +eco | B57: -0.35033333 | C57: -0.36266667
A58: -eco | B58: -0.5895 | C58: -0.612
A59: +fam | B59: -0.7605 | C59: -0.779
A60: -fam | B60: -0.23633333 | C60: -0.25133333

Sheet 9.AAG_Meta
C1: 1G1T1C ► 9.01 ANALISIS META-ADJETIVAL (AAG)
G2: Matriz ID: | H2: 1g1t1c (G2-T1-C1)
G3: Etapa: | H3: T1 - Diagnóstico Base | K3: Proyecto: | L3: Dossier Analítico NEX_ORD
C4: SIMULACIÓN IN SILICO Datos Anonimizados | G4: Motor Core: | H4: NEX_ORD Platinum v6.0 | K4: Analizado: | L4: 260829_154156
G5: Path Audit: | H5: .../05_Output/FULL_TABLES_1g1t1c.xlsx | K5: Protocolo: | L5: DOI 10.5281/zenodo.189416.1
A7: ► 9.01 AAG META
A8: Sujeto | B8: Dif | C8: n_sujeto | D8: edu | E8: eco | F8: fam
A9: 1 | B9: 1 | D9: 0 | E9: 2 | F9: 1
B10: a_de 1 | C10: 2 | D10: 0.5 | E10: 0.5 | F10: 0.5
B11: o_de 1 | C11: 2 | D11: 0.5 | E11: 0.5 | F11: 0.5
B12: a - o | D12: 0 | E12: 0 | F12: 0
A13: 2 | B13: 2 | D13: 1 | E13: 3 | F13: 2
B14: a_de 2 | C14: 3 | D14: -0.33333333 | E14: -0.33333333 | F14: -0.33333333
B15: o_de 2 | C15: 2 | D15: -0.5 | E15: -0.5 | F15: -0.5
B16: a - o | D16: 0.16666667 | E16: 0.16666667 | F16: 0.16666667
A17: 3 | B17: 3 | D17: 0 | E17: 4 | F17: 3
B18: a_de 3 | C18: 2 | D18: 0.5 | E18: -1.50* | F18: -1.50*
B19: o_de 3 | C19: 2 | D19: 0.5 | E19: -1.50* | F19: -1.50*
B20: a - o | D20: 0 | E20: 0 | F20: 0
A21: 4 | B21: 4 | D21: 1 | E21: 2 | F21: 4
B22: a_de 4 | C22: 2 | D22: -0.5 | E22: 0.5 | F22: -2.50*
B23: o_de 4 | C23: 2 | D23: -0.5 | E23: 0.5 | F23: -2.50*
B24: a - o | D24: 0 | E24: 0 | F24: 0
A25: 5 | B25: 5 | D25: 0 | E25: 3 | F25: 1
B26: a_de 5 | C26: 2 | D26: 0.5 | E26: -0.5 | F26: 0.5
B27: o_de 5 | C27: 2 | D27: 0.5 | E27: -0.5 | F27: 0.5
B28: a - o | D28: 0 | E28: 0 | F28: 0

Sheet 9.AAG_Meta_Charts
C1: 1G1T1C ► 9.02 Histogramas AAG Meta
G2: Matriz ID: | H2: 1g1t1c (G2-T1-C1)
G3: Etapa: | H3: T1 - Diagnóstico Base | K3: Proyecto: | L3: Dossier Analítico NEX_ORD
C4: SIMULACIÓN IN SILICO Datos Anonimizados | G4: Motor Core: | H4: NEX_ORD Platinum v6.0 | K4: Analizado: | L4: 260829_154156
G5: Path Audit: | H5: .../05_Output/FULL_TABLES_1g1t1c.xlsx | K5: Protocolo: | L5: DOI 10.5281/zenodo.189416.1

Sheet 11.CLUSTERS
C1: 1G1T1C ► 11.CLUSTERS
G2: Matriz ID: | H2: 1g1t1c (G2-T1-C1)
G3: Etapa: | H3: T1 - Diagnóstico Base | K3: Proyecto: | L3: Dossier Analítico NEX_ORD
C4: SIMULACIÓN IN SILICO Datos Anonimizados | G4: Motor Core: | H4: NEX_ORD Platinum v6.0 | K4: Analizado: | L4: 260829_154156
G5: Path Audit: | H5: .../05_Output/FULL_TABLES_1g1t1c.xlsx | K5: Protocolo: | L5: DOI 10.5281/zenodo.189416.1
A7: ► 11.01 CLUSTERS | F7: ► 11.02 CLUSTERS DENSIDADES SDA / SRC
A9: ID_Sujeto | B9: K=2 | C9: K=3 | D9: K=4 | F9: ID_Sujeto | G9: K2_SDA | H9: K2_SRC | I9: K3_SDA | J9: K3_SRC | K9: K4_SDA | L9: K4_SRC
A10: 1 | B10: 1 | C10: 1 | D10: 1 | F10: 1 | G10: -0.64128852 | H10: -0.67319987 | I10: -0.64128852 | J10: -0.67319987 | K10: -0.33827253 | L10: -0.35331473
A11: 5 | B11: 1 | C11: 1 | D11: 2 | F11: 5 | G11: -0.64128852 | H11: -0.67319987 | I11: -0.64128852 | J11: -0.67319987 | K11: -0.94430451 | L11: -0.993085
A12: 2 | B12: 2 | C12: 2 | D12: 3 | F12: 2 | G12: -0.72342006 | H12: -0.74503999 | I12: -0.38177633 | J12: -0.35519384 | K12: -0.38177633 | L12: -0.35519384
A13: 3 | B13: 2 | C13: 2 | D13: 3 | F13: 3 | G13: -0.72342006 | H13: -0.74503999 | I13: -0.38177633 | J13: -0.35519384 | K13: -0.38177633 | L13: -0.35519384
A14: 4 | B14: 2 | C14: 3 | D14: 4 | F14: 4 | G14: -0.72342006 | H14: -0.74503999 | I14: -1.4067075 | J14: -1.5247323 | K14: -1.4067075 | L14: -1.5247323
A18: ► 11.03 DENDROGRAMA (CAJ)
A45: ► 11.04 SUBGRUPOS - TAXONOMÍA DE GRUPALIDADES
A47: TIPO DE GRUPALIDAD | E47: INDICADORES CLAVE (NEX_ORD 2026)
A48: 1. LA CLASE CRISTALINA (Grupalidad Integrada) | E48: Recl_E ↑↑, TrS_pE ↑↑, FaP_E ↓↓ Alta cohesión en los K-clusters principales. Grupo sano y transparente.
A50: 2. EL ARCHIPIÉLAGO (Grupalidad Fragmentada) | E50: Recl_E ↑, OpS_E ↑ Presencia de subgrupos múltiples densos pero aislados (N_GRUMOS > 3). Faltan puentes.
A52: 3. LA NIEBLA COGNITIVA (Grupalidad Disociada) | E52: FaP_E ↑↑, TrS_pE ↓↓ Repulsiones Activas (R) dispersas y bajas, pero [R] (Percibidas) difusas. Falsas percepciones dominan.
A54: 4. EL AGUJERO NEGRO (Grupalidad Conflictiva) | E54: IS ↑↑, SS ↓↓, Recl_R ↑↑ Tensión Sociométrica Alta. Alta Reciprocidad en Relegamientos. Conflictividad estructural.
A58: ► 11.05 ESCÁNER DE ESCALABILIDAD (REDES DE SINTONÍA Y NODOS PUENTE)
A60: RANKING DE NÚCLEOS DENSOS (Facciones Solapadas)
A61: Tam (k) | B61: Opción | C61: SDR Interna | D61: Integrantes (Nodos Puente)
A62: 2 | B62: Top 1 | C62: 5.308 | D62: 4, 5
A63: 2 | B63: Top 2 | C63: 5 | D63: 2, 3
A64: 2 | B64: Top 3 | C64: 3.257 | D64: 1, 4
A65: 3 | B65: Top 1 | C65: 2.654 | D65: 1, 2, 3
A66: 3 | B66: Top 2 | C66: 1.153 | D66: 2, 3, 5
A67: 3 | B67: Top 3 | C67: 0.754 | D67: 1, 4, 5
A68: 4 | B68: Top 1 | C68: 0.41 | D68: 1, 2, 3, 5
A69: 4 | B69: Top 2 | C69: 0.228 | D69: 1, 2, 3, 4
A70: 4 | B70: Top 3 | C70: -0.181 | D70: 2, 3, 4, 5
A71: 5 | B71: Top 1 | C71: -0.352 | D71: 1, 2, 3, 4, 5
A73: CODO DE SATURACIÓN DETECTADO EN k=3 SUJETOS.
A76: ► 11.06 SINTONÍA GRUPAL (PG-S) Y CLASIFICACIÓN DE NODOS
A78: ÍNDICE DE RESONANCIA RELACIONAL (IRR): | E78: 1.82
A80: ID Sujeto | B80: Rol Estructural (PG-S)
A81: 1 | B81: Nodo Puente (Pivote)
A82: 2 | B82: Nodo Puente (Pivote)
A83: 3 | B83: Nodo Puente (Pivote)
A84: 4 | B84: Nodo de Anclaje (Resistencia)
A85: 5 | B85: Nodo de Anclaje (Resistencia)

Sheet 12.INDICES
C1: 1G1T1C ► 12.INDICES
G2: Matriz ID: | H2: 1g1t1c (G2-T1-C1)
G3: Etapa: | H3: T1 - Diagnóstico Base | K3: Proyecto: | L3: Dossier Analítico NEX_ORD
C4: SIMULACIÓN IN SILICO Datos Anonimizados | G4: Motor Core: | H4: NEX_ORD Platinum v6.0 | K4: Analizado: | L4: 260829_154156
G5: Path Audit: | H5: .../05_Output/FULL_TABLES_1g1t1c.xlsx | K5: Protocolo: | L5: DOI 10.5281/zenodo.189416.1
A7: ► 12.01 INDICES GRUPALES TRADICIONALES
A9: IND | C9: Numerador | D9: Denominador | E9: Grupo | F9: 1 | G9: 2 | H9: 3 | I9: 4 | J9: 5
A10: I1 | B10: percep_E | C10: <. | D10: n | F10: 0.25 | G10: 0.5 | H10: 0.25 | I10: 0.25 | J10: 0.25
A11: I2 | B11: Elección | C11: E. | D11: n | F11: 0.5 | G11: 0.75 | H11: 0.5 | I11: 0.5 | J11: 0.5
A12: I3 | B12: Repulsión | C12: R. | D12: n | F12: 0.5 | G12: 0.5 | H12: 0.5 | I12: 0.5 | J12: 0.5
A13: I4 | B13: percep_R | C13: [. | D13: n | F13: 0.25 | G13: 0.25 | H13: 0.25 | I13: 0.25 | J13: 0.25
A14: I5 | B14: Recl_pE | C14: <.> | D14: <. | F14: 0.775 | G14: 0.85 | H14: 0.775 | I14: 0.775 | J14: 0.775
A15: I6 | B15: Recl_E | C15: Ee | D15: E. | F15: 0.85 | G15: 0.925 | H15: 0.85 | I15: 0.85 | J15: 0.85
A16: I7 | B16: Recl_R | C16: Rr | D16: R. | F16: 0.5 | G16: 0.5 | H16: 0.85 | I16: 0.85 | J16: 0.85
A17: I8 | B17: Recl_pR | C17: [.] | D17: [. | F17: 0.775 | G17: 0.075 | H17: 0.775 | I17: 0.775 | J17: 0.775
A18: I9 | B18: REP_E | C18: <.e | D18: < | F18: 0.775 | G18: 0.85 | H18: 0.775 | I18: 0.775 | J18: 0.775
A19: I10 | B19: REP_pE | C19: <.e | D19: e | F19: 0.5 | G19: 0.69166667 | H19: 0.5 | I19: 0.5 | J19: 0.5
A20: I11 | B20: REP_pR | C20: [.r | D20: r
A21: I12 | B21: REP_R | C21: [.r | D21: [
A22: I13 | B22: TrS_pE | C22: E.> | D22: > | F22: 0.5 | G22: 0.69166667 | H22: 0.5 | I22: 0.5 | J22: 0.5
A23: I14 | B23: TrS_E | C23: E.> | D23: E. | F23: 0.775 | G23: 0.85 | H23: 0.775 | I23: 0.775 | J23: 0.775
A24: I15 | B24: TrS_R | C24: R.] | D24: R.
A25: I16 | B25: TsS_pR | C25: R.] | D25: ]
A26: I17 | B26: FaP_pE | C26: <.r | D26: <.
A27: I18 | B27: FaP_pR | C27: ].e | D27: [.
A28: I19 | B28: OpS_pE | C28: <]/< | F28: 0.075 | G28: 0.15 | H28: 0.075 | I28: 0.075 | J28: 0.075
A29: I20 | B29: OpS_E | C29: E.r | D29: E. | F29: 0.15 | G29: 0.225 | H29: 0.15 | I29: 0.15 | J29: 0.15
A30: I21 | B30: OpS_R | C30: R.e | D30: R. | F30: 0.15 | G30: 0.15 | H30: 0.15 | I30: 0.15 | J30: 0.15
A31: I22 | B31: OpS_pR | C31: [>]/[ | F31: 0.075 | G31: 0.075 | H31: 0.075 | I31: 0.075 | J31: 0.075
A32: I23 | B32: SS | C32: e++>+r+ | D32: e++>+r+ | F32: 0.25 | G32: 0.5 | H32: 0 | I32: -0.25 | J32: -0.25
A33: I24 | B33: LID1 | C33: LIDERAZGO
A34: I25 | B34: LID2 | C34: LIDERAZGO
A35: I26 | B35: PoD1 | C35: PODER | F35: 0 | G35: 0 | H35: 0 | I35: 0 | J35: 0
A36: I27 | B36: PoD2 | C36: PODER | F36: 0 | G36: 0 | H36: 0 | I36: 0 | J36: 0
A37: I28 | B37: DIAG | C37: DIAG
A38: I29 | B38: SIG_B | C38: SIG_B
A39: I30 | B39: CRI | C39: CRI
A40: I31 | B40: K_INF | C40: K_INF
A43: ► 12.02 INDICES MORENO DESCRIPCION
A44: ID | B44: Sigla (DA/REC) | C44: Descripcion | D44: formula | E44: Rango
A47: ► 12.03 INDICES AVANZADOS DESCRIPCION
A48: ID | B48: Sigla | C48: Autor | D48: Descripción y Significado | E48: Procedimiento de Cálculo | F48: Valores Grupo | G48: Valores Individuo

Sheet 10.PCA_coord
C1: 1G1T1C ► 10.01 PCA_COORD
G2: Matriz ID: | H2: 1g1t1c (G2-T1-C1)
G3: Etapa: | H3: T1 - Diagnóstico Base | K3: Proyecto: | L3: Dossier Analítico NEX_ORD
C4: SIMULACIÓN IN SILICO Datos Anonimizados | G4: Motor Core: | H4: NEX_ORD Platinum v6.0 | K4: Analizado: | L4: 260829_154156
G5: Path Audit: | H5: .../05_Output/FULL_TABLES_1g1t1c.xlsx | K5: Protocolo: | L5: DOI 10.5281/zenodo.189416.1
A7: ► 10.01 Coordenadas e inercias FILAS ACTIVAS | R7: ► TABLA EXTRAC. DATOS ORIGINALES (SDR)
A9: ID_Sujeto | B9: En 1 | E9: En 2 | H9: En 3 | K9: En 4 | N9: En 5 | R9: Sujeto | S9: 1 | T9: 2 | U9: 3 | V9: 4 | W9: 5
B10: COR | C10: CTR | D10: COS | E10: COR | F10: CTR | G10: COS | H10: COR | I10: CTR | J10: COS | K10: COR | L10: CTR | M10: COS | N10: COR | O10: CTR | P10: COS | R10: 1 | S10: 15.2 | T10: 1.98 | U10: 0 | V10: -4.7 | W10: -12.82
A11: 1 | B11: -0.44242038 | C11: 9.1422714 | D11: 44.962054 | E11: 0.47271406 | F11: 34.927587 | G11: 51.330196 | H11: 0.025929989 | I11: 0.2726731 | J11: 0.15444738 | K11: -0.12437357 | L11: 34.240993 | M11: 3.5533019 | R11: 2 | S11: 1.98 | T11: 0 | U11: 15.2 | V11: -11.7 | W11: -4.7
A12: 2 | B12: -0.50150725 | C12: 11.953319 | D12: 59.414096 | E12: -0.19125487 | F12: 5.8176391 | G12: 8.640922 | H12: -0.36429287 | I12: 54.763246 | J12: 31.349917 | K12: 0.050189693 | L12: 5.6737399 | M12: 0.59506463 | R12: 3 | S12: 0 | T12: 15.2 | U12: 1.98 | V12: -12.82 | W12: -7.96
A13: 3 | B13: -0.58953294 | C13: 15.404427 | D13: 68.059498 | E13: -0.20231236 | F13: 6.0710233 | G13: 8.0152561 | H13: 0.34008451 | I13: 44.509926 | J13: 22.648856 | K13: 0.0807338 | L13: 13.691356 | M13: 1.2763899 | R13: 4 | S13: -4.59 | T13: -11.26 | U13: -12.84 | V13: 15.2 | W13: 1.98
A14: 4 | B14: 0.99009747 | C14: 37.778634 | D14: 84.573399 | E14: 0.4075092 | F14: 21.416716 | G14: 14.326916 | H14: -0.0099030172 | I14: 0.032815513 | J14: 0.0084608296 | K14: 0.11246517 | L14: 23.101104 | M14: 1.0912242 | R14: 5 | S14: -12.82 | T14: -4.44 | U14: -8.07 | V14: 1.98 | W14: 15.2
A15: 5 | B15: 0.79209855 | C15: 25.721349 | D15: 71.93968 | E15: -0.48120136 | F15: 31.767035 | G15: 26.549953 | H15: 0.034404982 | I15: 0.42133909 | J15: 0.13572278 | K15: -0.10949395 | L15: 23.292806 | M15: 1.3746442
A18: ► 10.02 Coordenadas e inercias COLUMNAS ACTIVAS
A20: ID_Sujeto | B20: En 1 | E20: En 2 | H20: En 3 | K20: En 4 | N20: En 5
B21: COR | C21: CTR | D21: COS | E21: COR | F21: CTR | G21: COS | H21: COR | I21: CTR | J21: COS | K21: COR | L21: CTR | M21: COS | N21: COR | O21: CTR | P21: COS
A22: 1 | B22: -0.44374053 | C22: 9.2127531 | D22: 45.192232 | E22: 0.47190514 | F22: 34.868105 | G22: 51.111074 | H22: -0.026258581 | I22: 0.28010929 | J22: 0.15825159 | K22: -0.12416617 | L22: 34.18567 | M22: 3.5384427
A23: 2 | B23: -0.47907163 | C23: 11.02524 | D23: 57.358907 | E23: -0.18594928 | F23: 5.5585798 | G23: 8.6414967 | H23: 0.36543636 | I23: 55.701187 | J23: 33.37517 | K23: 0.049985114 | L23: 5.6881993 | M23: 0.62442652
A24: 3 | B24: -0.60319977 | C24: 16.092338 | D24: 69.204684 | E24: -0.20489874 | F24: 6.2138834 | G24: 7.9853093 | H24: -0.3365858 | I24: 43.505302 | J24: 21.547889 | K24: 0.081459797 | L24: 13.908803 | M24: 1.2621175
A25: 4 | B25: 0.99981232 | C25: 38.136174 | D25: 84.673327 | E25: 0.41021468 | F25: 21.483758 | G25: 14.253846 | H25: 0.0029034349 | I25: 0.0027924031 | J25: 0.00071405857 | K25: 0.11250333 | L25: 22.884276 | M25: 1.0721126
A26: 5 | B26: 0.79025878 | C26: 25.533494 | D26: 71.703581 | E26: -0.48266971 | F26: 31.875674 | G26: 26.748676 | H26: -0.037925519 | I26: 0.51060896 | J26: 0.16514493 | K26: -0.10973542 | L26: 23.333052 | M26: 1.3825978

Sheet 13.Difracción
C1: 1G1T1C Difracción
G2: Matriz ID: | H2: 1g1t1c (G2-T1-C1)
G3: Etapa: | H3: T1 - Diagnóstico Base | K3: Proyecto: | L3: Dossier Analítico NEX_ORD
C4: SIMULACIÓN IN SILICO Datos Anonimizados | G4: Motor Core: | H4: NEX_ORD Platinum v6.0 | K4: Analizado: | L4: 260829_154156
G5: Path Audit: | H5: .../05_Output/FULL_TABLES_1g1t1c.xlsx | K5: Protocolo: | L5: DOI 10.5281/zenodo.189416.1
A8: 13.01 Difracción
A11: ► 13.01 DENSIDAD NETA (SDR) - ENERGÍA ÚTIL | R11: ► 13.02
B12: e | C12: ? | D12: r | E12: > | F12: ! | G12: ] | H12: e> | I12: e! | J12: e] | K12: ?> | L12: ?! | M12: ?] | N12: r> | O12: r! | P12: r] | S12: e | T12: >
A13: E | B13: 4.69 | E13: 4.69 | H13: 4.69 | R13: E | S13: -3.22 | T13: -3.22
A14: ¿ | R14: <E | S14: -3.22 | T14: -3.22
A15: R | D15: -7.91 | G15: -7.91 | P15: -7.91
A16: < | B16: 4.69 | E16: 4.69 | H16: 4.69
A17: ¡
A18: [ | D18: -7.91 | G18: -7.91 | P18: -7.91
A19: <E | B19: 4.69 | E19: 4.69 | H19: 4.69
A20: <¿
A21: <R
A22: ¡E
A23: ¡¿
A24: ¡R
A25: [E
A26: [¿
A27: [R | D27: -7.91 | G27: -7.91 | P27: -7.91
A30: ► 13.03 FRECUENCIA DE IMPACTOS | R30: ► 13.04
B31: e | C31: ? | D31: r | E31: > | F31: ! | G31: ] | H31: e> | I31: e! | J31: e] | K31: ?> | L31: ?! | M31: ?] | N31: r> | O31: r! | P31: r] | S31: e | T31: >
A32: E | B32: 2 | E32: 2 | H32: 2 | R32: E | S32: 6 | T32: 6
A33: ¿ | R33: <E | S33: 6 | T33: 6
A34: R | D34: 4 | G34: 4 | P34: 4
A35: < | B35: 2 | E35: 2 | H35: 2
A36: ¡
A37: [ | D37: 4 | G37: 4 | P37: 4
A38: <E | B38: 2 | E38: 2 | H38: 2
A39: <¿
A40: <R
A41: ¡E
A42: ¡¿
A43: ¡R
A44: [E
A45: [¿
A46: [R | D46: 4 | G46: 4 | P46: 4
A49: ► 13.05 DENSIDAD BRUTA (BDR) - TRABAJO TOTAL | R49: ► 13.06
B50: e | C50: ? | D50: r | E50: > | F50: ! | G50: ] | H50: e> | I50: e! | J50: e] | K50: ?> | L50: ?! | M50: ?] | N50: r> | O50: r! | P50: r] | S50: e | T50: >
A51: E | B51: 4.69 | E51: 4.69 | H51: 4.69 | R51: E | S51: 12.6 | T51: 12.6
A52: ¿ | R52: <E | S52: 12.6 | T52: 12.6
A53: R | D53: 7.91 | G53: 7.91 | P53: 7.91
A54: < | B54: 4.69 | E54: 4.69 | H54: 4.69
A55: ¡
A56: [ | D56: 7.91 | G56: 7.91 | P56: 7.91
A57: <E | B57: 4.69 | E57: 4.69 | H57: 4.69
A58: <¿
A59: <R
A60: ¡E
A61: ¡¿
A62: ¡R
A63: [E
A64: [¿
A65: [R | D65: 7.91 | G65: 7.91 | P65: 7.91
A68: ► 13.07 DESGASTE TERMODINÁMICO (BDR - |SDR|) | R68: ► 13.08
B69: e | C69: ? | D69: r | E69: > | F69: ! | G69: ] | H69: e> | I69: e! | J69: e] | K69: ?> | L69: ?! | M69: ?] | N69: r> | O69: r! | P69: r] | S69: e | T69: >
A70: E | R70: E | S70: 0 | T70: 0
A71: ¿ | R71: <E | S71: 0 | T71: 0
A72: R
A73: <
A74: ¡
A75: [
A76: <E
A77: <¿
A78: <R
A79: ¡E
A80: ¡¿
A81: ¡R
A82: [E
A83: [¿
A84: [R

Sheet 14.Rejillas
C1: 1G1T1C Rejillas
G2: Matriz ID: | H2: 1g1t1c (G2-T1-C1)
G3: Etapa: | H3: T1 - Diagnóstico Base | K3: Proyecto: | L3: Dossier Analítico NEX_ORD
C4: SIMULACIÓN IN SILICO Datos Anonimizados | G4: Motor Core: | H4: NEX_ORD Platinum v6.0 | K4: Analizado: | L4: 260829_154156
G5: Path Audit: | H5: .../05_Output/FULL_TABLES_1g1t1c.xlsx | K5: Protocolo: | L5: DOI 10.5281/zenodo.189416.1
A8: ► 14.01 REJILLA TOPOGRAFICA DE FRECUENCIAS (15X15) | W8: ► 14.02 REJILLA TOPOGRAFICA DE DENSIDAD BRUTA (15X15)
B9: e | C9: ? | D9: r | E9: > | F9: ! | G9: ] | H9: e> | I9: e! | J9: e] | K9: ?> | L9: ?! | M9: ?] | N9: r> | O9: r! | P9: r] | Q9: Σ | X9: e | Y9: ? | Z9: r | AA9: > | AB9: ! | AC9: ] | AD9: e> | AE9: e! | AF9: e] | AG9: ?> | AH9: ?! | AI9: ?] | AJ9: r> | AK9: r! | AL9: r] | AM9: Σ
A10: E | B10: 2 | E10: 2 | H10: 2 | Q10: 6 | W10: E | X10: 4.69 | AA10: 4.69 | AD10: 4.69 | AM10: 14.07
A11: ¿ | W11: ¿
A12: R | D12: 4 | G12: 4 | P12: 4 | Q12: 12 | W12: R | Z12: 7.91 | AC12: 7.91 | AL12: 7.91 | AM12: 23.73
A13: < | B13: 2 | E13: 2 | H13: 2 | Q13: 6 | W13: < | X13: 4.69 | AA13: 4.69 | AD13: 4.69 | AM13: 14.07
A14: ¡ | W14: ¡
A15: [ | D15: 4 | G15: 4 | P15: 4 | Q15: 12 | W15: [ | Z15: 7.91 | AC15: 7.91 | AL15: 7.91 | AM15: 23.73
A16: <E | B16: 2 | E16: 2 | H16: 2 | Q16: 6 | W16: <E | X16: 4.69 | AA16: 4.69 | AD16: 4.69 | AM16: 14.07
A17: <¿ | W17: <¿
A18: <R | W18: <R
A19: ¡E | W19: ¡E
A20: ¡¿ | W20: ¡¿
A21: ¡R | W21: ¡R
A22: [E | W22: [E
A23: [¿ | W23: [¿
A24: [R | D24: 4 | G24: 4 | P24: 4 | Q24: 12 | W24: [R | Z24: 7.91 | AC24: 7.91 | AL24: 7.91 | AM24: 23.73
A25: Σ | B25: 6 | D25: 12 | E25: 6 | G25: 12 | H25: 6 | P25: 12 | Q25: 54 | W25: Σ | X25: 14.07 | Z25: 23.73 | AA25: 14.07 | AC25: 23.73 | AD25: 14.07 | AL25: 23.73 | AM25: 113.4
A29: ► 14.03 REJILLA FACTUAL - PRISMA 1 - ACTIVO (A4 x A1) | W29: ► 14.04 REJILLA FACTUAL - PRISMA 1 - ACTIVO (A4 x A1)
B30: E | C30: ¿ | D30: R | E30: < | F30: ¡ | G30: [ | H30: e | I30: ? | J30: r | K30: > | L30: ! | M30: ] | N30: Σ | X30: E | Y30: ¿ | Z30: R | AA30: < | AB30: ¡ | AC30: [ | AD30: e | AE30: ? | AF30: r | AG30: > | AH30: ! | AI30: ] | AJ30: Σ
A31: 1 | D31: 1 | G31: 1 | N31: 2 | W31: 1 | Z31: 1.98 | AC31: 1.98 | AJ31: 3.96
A32: 2 | B32: 1 | E32: 1 | N32: 2 | W32: 2 | X32: 2.35 | AA32: 2.35 | AJ32: 4.7
A33: 3 | B33: 1 | D33: 1 | E33: 1 | G33: 1 | N33: 4 | W33: 3 | X33: 2.35 | Z33: 1.98 | AA33: 2.35 | AC33: 1.98 | AJ33: 8.66
A34: 4 | D34: 1 | G34: 1 | N34: 2 | W34: 4 | Z34: 1.98 | AC34: 1.98 | AJ34: 3.96
A35: 5 | D35: 1 | G35: 1 | N35: 2 | W35: 5 | Z35: 1.98 | AC35: 1.98 | AJ35: 3.96
A36: Σ | B36: 2 | D36: 4 | E36: 2 | G36: 4 | N36: 12 | W36: Σ | X36: 4.7 | Z36: 7.92 | AA36: 4.7 | AC36: 7.92 | AJ36: 25.24
A40: ► 14.05 REJILLA FACTUAL - PRISMA 2 - PASIVO (A2 x A3) | W40: ► 14.06 REJILLA FACTUAL - PRISMA 2 - PASIVO (A2 x A3)
B41: E | C41: ¿ | D41: R | E41: < | F41: ¡ | G41: [ | H41: e | I41: ? | J41: r | K41: > | L41: ! | M41: ] | N41: Σ | X41: E | Y41: ¿ | Z41: R | AA41: < | AB41: ¡ | AC41: [ | AD41: e | AE41: ? | AF41: r | AG41: > | AH41: ! | AI41: ] | AJ41: Σ
A42: 1 | J42: 1 | M42: 1 | N42: 2 | W42: 1 | AF42: 1.98 | AI42: 1.98 | AJ42: 3.96
A43: 2 | H43: 1 | K43: 1 | N43: 2 | W43: 2 | AD43: 2.35 | AG43: 2.35 | AJ43: 4.7
A44: 3 | H44: 1 | J44: 1 | K44: 1 | M44: 1 | N44: 4 | W44: 3 | AD44: 2.35 | AF44: 1.98 | AG44: 2.35 | AI44: 1.98 | AJ44: 8.66
A45: 4 | J45: 1 | M45: 1 | N45: 2 | W45: 4 | AF45: 1.99 | AI45: 1.99 | AJ45: 3.98
A46: 5 | J46: 1 | M46: 1 | N46: 2 | W46: 5 | AF46: 1.98 | AI46: 1.98 | AJ46: 3.96
A47: Σ | H47: 2 | J47: 4 | K47: 2 | M47: 4 | N47: 12 | W47: Σ | AD47: 4.7 | AF47: 7.93 | AG47: 4.7 | AI47: 7.93 | AJ47: 25.26
A51: ► 14.07 REJILLA PERCEPTUAL - PRISMA 3 - EXTERNO (A4 x A2) | W51: ► 14.08 REJILLA PERCEPTUAL - PRISMA 3 - EXTERNO (A4 x A2)
B52: E | C52: ¿ | D52: R | E52: < | F52: ¡ | G52: [ | H52: e | I52: ? | J52: r | K52: > | L52: ! | M52: ] | N52: Σ | X52: E | Y52: ¿ | Z52: R | AA52: < | AB52: ¡ | AC52: [ | AD52: e | AE52: ? | AF52: r | AG52: > | AH52: ! | AI52: ] | AJ52: Σ
A53: 1 | G53: 1 | J53: 1 | N53: 2 | W53: 1 | AC53: 1.98 | AF53: 1.98 | AJ53: 3.96
A54: 2 | E54: 1 | H54: 1 | N54: 2 | W54: 2 | AA54: 2.35 | AD54: 2.35 | AJ54: 4.7
A55: 3 | E55: 1 | G55: 1 | H55: 1 | J55: 1 | N55: 4 | W55: 3 | AA55: 2.35 | AC55: 1.98 | AD55: 2.35 | AF55: 1.98 | AJ55: 8.66
A56: 4 | G56: 1 | J56: 1 | N56: 2 | W56: 4 | AC56: 1.98 | AF56: 1.99 | AJ56: 3.97
A57: 5 | G57: 1 | J57: 1 | N57: 2 | W57: 5 | AC57: 1.98 | AF57: 1.98 | AJ57: 3.96
A58: Σ | E58: 2 | G58: 4 | H58: 2 | J58: 4 | N58: 12 | W58: Σ | AA58: 4.7 | AC58: 7.92 | AD58: 4.7 | AF58: 7.93 | AJ58: 25.25
A62: ► 14.09 REJILLA PERCEPTUAL - PRISMA 4 - INTERNO (A1 x A3) | W62: ► 14.10 REJILLA PERCEPTUAL - PRISMA 4 - INTERNO (A1 x A3)
B63: E | C63: ¿ | D63: R | E63: < | F63: ¡ | G63: [ | H63: e | I63: ? | J63: r | K63: > | L63: ! | M63: ] | N63: Σ | X63: E | Y63: ¿ | Z63: R | AA63: < | AB63: ¡ | AC63: [ | AD63: e | AE63: ? | AF63: r | AG63: > | AH63: ! | AI63: ] | AJ63: Σ
A64: 1 | D64: 1 | M64: 1 | N64: 2 | W64: 1 | Z64: 1.98 | AI64: 1.98 | AJ64: 3.96
A65: 2 | B65: 1 | K65: 1 | N65: 2 | W65: 2 | X65: 2.35 | AG65: 2.35 | AJ65: 4.7
A66: 3 | B66: 1 | D66: 1 | K66: 1 | M66: 1 | N66: 4 | W66: 3 | X66: 2.35 | Z66: 1.98 | AG66: 2.35 | AI66: 1.98 | AJ66: 8.66
A67: 4 | D67: 1 | M67: 1 | N67: 2 | W67: 4 | Z67: 1.98 | AI67: 1.99 | AJ67: 3.97
A68: 5 | D68: 1 | M68: 1 | N68: 2 | W68: 5 | Z68: 1.98 | AI68: 1.98 | AJ68: 3.96
A69: Σ | B69: 2 | D69: 4 | K69: 2 | M69: 4 | N69: 12 | W69: Σ | X69: 4.7 | Z69: 7.92 | AG69: 4.7 | AI69: 7.93 | AJ69: 25.25
A73: ► 14.11 REJILLA PERCEPTUAL - PRISMA 5 - PERCEPTUAL (A4 x A3) | W73: ► 14.12 REJILLA PERCEPTUAL - PRISMA 5 - PERCEPTUAL (A4 x A3)
B74: E | C74: ¿ | D74: R | E74: < | F74: ¡ | G74: [ | H74: e | I74: ? | J74: r | K74: > | L74: ! | M74: ] | N74: Σ | X74: E | Y74: ¿ | Z74: R | AA74: < | AB74: ¡ | AC74: [ | AD74: e | AE74: ? | AF74: r | AG74: > | AH74: ! | AI74: ] | AJ74: Σ
A75: 1 | G75: 1 | M75: 1 | N75: 2 | W75: 1 | AC75: 1.98 | AI75: 1.98 | AJ75: 3.96
A76: 2 | E76: 1 | K76: 1 | N76: 2 | W76: 2 | AA76: 2.35 | AG76: 2.35 | AJ76: 4.7
A77: 3 | E77: 1 | G77: 1 | K77: 1 | M77: 1 | N77: 4 | W77: 3 | AA77: 2.35 | AC77: 1.98 | AG77: 2.35 | AI77: 1.98 | AJ77: 8.66
A78: 4 | G78: 1 | M78: 1 | N78: 2 | W78: 4 | AC78: 1.98 | AI78: 1.99 | AJ78: 3.97
A79: 5 | G79: 1 | M79: 1 | N79: 2 | W79: 5 | AC79: 1.98 | AI79: 1.98 | AJ79: 3.96
A80: Σ | E80: 2 | G80: 4 | K80: 2 | M80: 4 | N80: 12 | W80: Σ | AA80: 4.7 | AC80: 7.92 | AG80: 4.7 | AI80: 7.93 | AJ80: 25.25
A84: ► 14.13 REJILLA FACTUAL - PRISMA 6 - FACTUAL (A1 x A2) | W84: ► 14.14 REJILLA FACTUAL - PRISMA 6 - FACTUAL (A1 x A2)
B85: E | C85: ¿ | D85: R | E85: < | F85: ¡ | G85: [ | H85: e | I85: ? | J85: r | K85: > | L85: ! | M85: ] | N85: Σ | X85: E | Y85: ¿ | Z85: R | AA85: < | AB85: ¡ | AC85: [ | AD85: e | AE85: ? | AF85: r | AG85: > | AH85: ! | AI85: ] | AJ85: Σ
A86: 1 | D86: 1 | J86: 1 | N86: 2 | W86: 1 | Z86: 1.98 | AF86: 1.98 | AJ86: 3.96
A87: 2 | B87: 1 | H87: 1 | N87: 2 | W87: 2 | X87: 2.35 | AD87: 2.35 | AJ87: 4.7
A88: 3 | B88: 1 | D88: 1 | H88: 1 | J88: 1 | N88: 4 | W88: 3 | X88: 2.35 | Z88: 1.98 | AD88: 2.35 | AF88: 1.98 | AJ88: 8.66
A89: 4 | D89: 1 | J89: 1 | N89: 2 | W89: 4 | Z89: 1.98 | AF89: 1.99 | AJ89: 3.97
A90: 5 | D90: 1 | J90: 1 | N90: 2 | W90: 5 | Z90: 1.98 | AF90: 1.98 | AJ90: 3.96
A91: Σ | B91: 2 | D91: 4 | H91: 2 | J91: 4 | N91: 12 | W91: Σ | X91: 4.7 | Z91: 7.92 | AD91: 4.7 | AF91: 7.93 | AJ91: 25.25

Sheet 15.Difr_Prismas
C1: 1G1T1C Difr. Prismas
G2: Matriz ID: | H2: 1g1t1c (G2-T1-C1)
G3: Etapa: | H3: T1 - Diagnóstico Base | K3: Proyecto: | L3: Dossier Analítico NEX_ORD
C4: SIMULACIÓN IN SILICO Datos Anonimizados | G4: Motor Core: | H4: NEX_ORD Platinum v6.0 | K4: Analizado: | L4: 260829_154156
G5: Path Audit: | H5: .../05_Output/FULL_TABLES_1g1t1c.xlsx | K5: Protocolo: | L5: DOI 10.5281/zenodo.189416.1
A8: 15.01 PRISMA 1 - ACTIVO (A4 x A1)
A11: ► 15.01 DENSIDAD NETA (SDR) - PRISMA 1 - ACTIVO (A4 x A1) | W11: ► 15.02 FRECUENCIA DE IMPACTOS
B12: E | C12: ¿ | D12: R | E12: Σ | F12: < | G12: ¡ | H12: [ | I12: Σ | J12: e | K12: ? | L12: r | M12: Σ | N12: > | O12: ! | P12: ] | Q12: Σ | X12: E | Y12: ¿ | Z12: R | AA12: Σ | AB12: < | AC12: ¡ | AD12: [ | AE12: Σ | AF12: e | AG12: ? | AH12: r | AI12: Σ | AJ12: > | AK12: ! | AL12: ] | AM12: Σ
A13: 1 | D13: -1.98 | E13: -1.98 | H13: -1.98 | I13: -1.98 | W13: 1 | Z13: 1 | AA13: 1 | AD13: 1 | AE13: 1
A14: 2 | B14: 2.35 | E14: 2.35 | F14: 2.35 | I14: 2.35 | W14: 2 | X14: 1 | AA14: 1 | AB14: 1 | AE14: 1
A15: 3 | B15: 2.35 | D15: -1.98 | E15: 0.37 | F15: 2.35 | H15: -1.98 | I15: 0.37 | W15: 3 | X15: 1 | Z15: 1 | AA15: 2 | AB15: 1 | AD15: 1 | AE15: 2
A16: 4 | D16: -1.98 | E16: -1.98 | H16: -1.98 | I16: -1.98 | W16: 4 | Z16: 1 | AA16: 1 | AD16: 1 | AE16: 1
A17: 5 | D17: -1.98 | E17: -1.98 | H17: -1.98 | I17: -1.98 | W17: 5 | Z17: 1 | AA17: 1 | AD17: 1 | AE17: 1
A21: ► 15.03 DENSIDAD BRUTA (BDR) | W21: ► 15.04 DESGASTE TERMODINÁMICO
B22: E | C22: ¿ | D22: R | E22: Σ | F22: < | G22: ¡ | H22: [ | I22: Σ | J22: e | K22: ? | L22: r | M22: Σ | N22: > | O22: ! | P22: ] | Q22: Σ | X22: E | Y22: ¿ | Z22: R | AA22: Σ | AB22: < | AC22: ¡ | AD22: [ | AE22: Σ | AF22: e | AG22: ? | AH22: r | AI22: Σ | AJ22: > | AK22: ! | AL22: ] | AM22: Σ
A23: 1 | D23: 1.98 | E23: 1.98 | H23: 1.98 | I23: 1.98 | W23: 1
A24: 2 | B24: 2.35 | E24: 2.35 | F24: 2.35 | I24: 2.35 | W24: 2
A25: 3 | B25: 2.35 | D25: 1.98 | E25: 4.33 | F25: 2.35 | H25: 1.98 | I25: 4.33 | W25: 3
A26: 4 | D26: 1.98 | E26: 1.98 | H26: 1.98 | I26: 1.98 | W26: 4
A27: 5 | D27: 1.98 | E27: 1.98 | H27: 1.98 | I27: 1.98 | W27: 5
A32: 15.02 PRISMA 2 - PASIVO (A2 x A3)
A35: ► 15.05 DENSIDAD NETA (SDR) - PRISMA 2 - PASIVO (A2 x A3) | W35: ► 15.06 FRECUENCIA DE IMPACTOS
B36: E | C36: ¿ | D36: R | E36: Σ | F36: < | G36: ¡ | H36: [ | I36: Σ | J36: e | K36: ? | L36: r | M36: Σ | N36: > | O36: ! | P36: ] | Q36: Σ | X36: E | Y36: ¿ | Z36: R | AA36: Σ | AB36: < | AC36: ¡ | AD36: [ | AE36: Σ | AF36: e | AG36: ? | AH36: r | AI36: Σ | AJ36: > | AK36: ! | AL36: ] | AM36: Σ
A37: 1 | L37: -1.98 | M37: -1.98 | P37: -1.98 | Q37: -1.98 | W37: 1 | AH37: 1 | AI37: 1 | AL37: 1 | AM37: 1
A38: 2 | J38: 2.35 | M38: 2.35 | N38: 2.35 | Q38: 2.35 | W38: 2 | AF38: 1 | AI38: 1 | AJ38: 1 | AM38: 1
A39: 3 | J39: 2.35 | L39: -1.98 | M39: 0.37 | N39: 2.35 | P39: -1.98 | Q39: 0.37 | W39: 3 | AF39: 1 | AH39: 1 | AI39: 2 | AJ39: 1 | AL39: 1 | AM39: 2
A40: 4 | L40: -1.99 | M40: -1.99 | P40: -1.99 | Q40: -1.99 | W40: 4 | AH40: 1 | AI40: 1 | AL40: 1 | AM40: 1
A41: 5 | L41: -1.98 | M41: -1.98 | P41: -1.98 | Q41: -1.98 | W41: 5 | AH41: 1 | AI41: 1 | AL41: 1 | AM41: 1
A45: ► 15.07 DENSIDAD BRUTA (BDR) | W45: ► 15.08 DESGASTE TERMODINÁMICO
B46: E | C46: ¿ | D46: R | E46: Σ | F46: < | G46: ¡ | H46: [ | I46: Σ | J46: e | K46: ? | L46: r | M46: Σ | N46: > | O46: ! | P46: ] | Q46: Σ | X46: E | Y46: ¿ | Z46: R | AA46: Σ | AB46: < | AC46: ¡ | AD46: [ | AE46: Σ | AF46: e | AG46: ? | AH46: r | AI46: Σ | AJ46: > | AK46: ! | AL46: ] | AM46: Σ
A47: 1 | L47: 1.98 | M47: 1.98 | P47: 1.98 | Q47: 1.98 | W47: 1
A48: 2 | J48: 2.35 | M48: 2.35 | N48: 2.35 | Q48: 2.35 | W48: 2
A49: 3 | J49: 2.35 | L49: 1.98 | M49: 4.33 | N49: 2.35 | P49: 1.98 | Q49: 4.33 | W49: 3
A50: 4 | L50: 1.99 | M50: 1.99 | P50: 1.99 | Q50: 1.99 | W50: 4
A51: 5 | L51: 1.98 | M51: 1.98 | P51: 1.98 | Q51: 1.98 | W51: 5
A56: 15.03 PRISMA 3 - EXTERNO (A4 x A2)
A59: ► 15.09 DENSIDAD NETA (SDR) - PRISMA 3 - EXTERNO (A4 x A2) | W59: ► 15.10 FRECUENCIA DE IMPACTOS
B60: E | C60: ¿ | D60: R | E60: Σ | F60: < | G60: ¡ | H60: [ | I60: Σ | J60: e | K60: ? | L60: r | M60: Σ | N60: > | O60: ! | P60: ] | Q60: Σ | X60: E | Y60: ¿ | Z60: R | AA60: Σ | AB60: < | AC60: ¡ | AD60: [ | AE60: Σ | AF60: e | AG60: ? | AH60: r | AI60: Σ | AJ60: > | AK60: ! | AL60: ] | AM60: Σ
A61: 1 | H61: -1.98 | I61: -1.98 | L61: -1.98 | M61: -1.98 | W61: 1 | AD61: 1 | AE61: 1 | AH61: 1 | AI61: 1
A62: 2 | F62: 2.35 | I62: 2.35 | J62: 2.35 | M62: 2.35 | W62: 2 | AB62: 1 | AE62: 1 | AF62: 1 | AI62: 1
A63: 3 | F63: 2.35 | H63: -1.98 | I63: 0.37 | J63: 2.35 | L63: -1.98 | M63: 0.37 | W63: 3 | AB63: 1 | AD63: 1 | AE63: 2 | AF63: 1 | AH63: 1 | AI63: 2
A64: 4 | H64: -1.98 | I64: -1.98 | L64: -1.99 | M64: -1.99 | W64: 4 | AD64: 1 | AE64: 1 | AH64: 1 | AI64: 1
A65: 5 | H65: -1.98 | I65: -1.98 | L65: -1.98 | M65: -1.98 | W65: 5 | AD65: 1 | AE65: 1 | AH65: 1 | AI65: 1
A69: ► 15.11 DENSIDAD BRUTA (BDR) | W69: ► 15.12 DESGASTE TERMODINÁMICO
B70: E | C70: ¿ | D70: R | E70: Σ | F70: < | G70: ¡ | H70: [ | I70: Σ | J70: e | K70: ? | L70: r | M70: Σ | N70: > | O70: ! | P70: ] | Q70: Σ | X70: E | Y70: ¿ | Z70: R | AA70: Σ | AB70: < | AC70: ¡ | AD70: [ | AE70: Σ | AF70: e | AG70: ? | AH70: r | AI70: Σ | AJ70: > | AK70: ! | AL70: ] | AM70: Σ
A71: 1 | H71: 1.98 | I71: 1.98 | L71: 1.98 | M71: 1.98 | W71: 1
A72: 2 | F72: 2.35 | I72: 2.35 | J72: 2.35 | M72: 2.35 | W72: 2
A73: 3 | F73: 2.35 | H73: 1.98 | I73: 4.33 | J73: 2.35 | L73: 1.98 | M73: 4.33 | W73: 3
A74: 4 | H74: 1.98 | I74: 1.98 | L74: 1.99 | M74: 1.99 | W74: 4
A75: 5 | H75: 1.98 | I75: 1.98 | L75: 1.98 | M75: 1.98 | W75: 5
A80: 15.04 PRISMA 4 - INTERNO (A1 x A3)
A83: ► 15.13 DENSIDAD NETA (SDR) - PRISMA 4 - INTERNO (A1 x A3) | W83: ► 15.14 FRECUENCIA DE IMPACTOS
B84: E | C84: ¿ | D84: R | E84: Σ | F84: < | G84: ¡ | H84: [ | I84: Σ | J84: e | K84: ? | L84: r | M84: Σ | N84: > | O84: ! | P84: ] | Q84: Σ | X84: E | Y84: ¿ | Z84: R | AA84: Σ | AB84: < | AC84: ¡ | AD84: [ | AE84: Σ | AF84: e | AG84: ? | AH84: r | AI84: Σ | AJ84: > | AK84: ! | AL84: ] | AM84: Σ
A85: 1 | D85: -1.98 | E85: -1.98 | P85: -1.98 | Q85: -1.98 | W85: 1 | Z85: 1 | AA85: 1 | AL85: 1 | AM85: 1
A86: 2 | B86: 2.35 | E86: 2.35 | N86: 2.35 | Q86: 2.35 | W86: 2 | X86: 1 | AA86: 1 | AJ86: 1 | AM86: 1
A87: 3 | B87: 2.35 | D87: -1.98 | E87: 0.37 | N87: 2.35 | P87: -1.98 | Q87: 0.37 | W87: 3 | X87: 1 | Z87: 1 | AA87: 2 | AJ87: 1 | AL87: 1 | AM87: 2
A88: 4 | D88: -1.98 | E88: -1.98 | P88: -1.99 | Q88: -1.99 | W88: 4 | Z88: 1 | AA88: 1 | AL88: 1 | AM88: 1
A89: 5 | D89: -1.98 | E89: -1.98 | P89: -1.98 | Q89: -1.98 | W89: 5 | Z89: 1 | AA89: 1 | AL89: 1 | AM89: 1
A93: ► 15.15 DENSIDAD BRUTA (BDR) | W93: ► 15.16 DESGASTE TERMODINÁMICO
B94: E | C94: ¿ | D94: R | E94: Σ | F94: < | G94: ¡ | H94: [ | I94: Σ | J94: e | K94: ? | L94: r | M94: Σ | N94: > | O94: ! | P94: ] | Q94: Σ | X94: E | Y94: ¿ | Z94: R | AA94: Σ | AB94: < | AC94: ¡ | AD94: [ | AE94: Σ | AF94: e | AG94: ? | AH94: r | AI94: Σ | AJ94: > | AK94: ! | AL94: ] | AM94: Σ
A95: 1 | D95: 1.98 | E95: 1.98 | P95: 1.98 | Q95: 1.98 | W95: 1
A96: 2 | B96: 2.35 | E96: 2.35 | N96: 2.35 | Q96: 2.35 | W96: 2
A97: 3 | B97: 2.35 | D97: 1.98 | E97: 4.33 | N97: 2.35 | P97: 1.98 | Q97: 4.33 | W97: 3
A98: 4 | D98: 1.98 | E98: 1.98 | P98: 1.99 | Q98: 1.99 | W98: 4
A99: 5 | D99: 1.98 | E99: 1.98 | P99: 1.98 | Q99: 1.98 | W99: 5
A104: 15.05 PRISMA 5 - PERCEPTUAL (A4 x A3)
A107: ► 15.17 DENSIDAD NETA (SDR) - PRISMA 5 - PERCEPTUAL (A4 x A3) | W107: ► 15.18 FRECUENCIA DE IMPACTOS
B108: E | C108: ¿ | D108: R | E108: Σ | F108: < | G108: ¡ | H108: [ | I108: Σ | J108: e | K108: ? | L108: r | M108: Σ | N108: > | O108: ! | P108: ] | Q108: Σ | X108: E | Y108: ¿ | Z108: R | AA108: Σ | AB108: < | AC108: ¡ | AD108: [ | AE108: Σ | AF108: e | AG108: ? | AH108: r | AI108: Σ | AJ108: > | AK108: ! | AL108: ] | AM108: Σ
A109: 1 | H109: -1.98 | I109: -1.98 | P109: -1.98 | Q109: -1.98 | W109: 1 | AD109: 1 | AE109: 1 | AL109: 1 | AM109: 1
A110: 2 | F110: 2.35 | I110: 2.35 | N110: 2.35 | Q110: 2.35 | W110: 2 | AB110: 1 | AE110: 1 | AJ110: 1 | AM110: 1
A111: 3 | F111: 2.35 | H111: -1.98 | I111: 0.37 | N111: 2.35 | P111: -1.98 | Q111: 0.37 | W111: 3 | AB111: 1 | AD111: 1 | AE111: 2 | AJ111: 1 | AL111: 1 | AM111: 2
A112: 4 | H112: -1.98 | I112: -1.98 | P112: -1.99 | Q112: -1.99 | W112: 4 | AD112: 1 | AE112: 1 | AL112: 1 | AM112: 1
A113: 5 | H113: -1.98 | I113: -1.98 | P113: -1.98 | Q113: -1.98 | W113: 5 | AD113: 1 | AE113: 1 | AL113: 1 | AM113: 1
A117: ► 15.19 DENSIDAD BRUTA (BDR) | W117: ► 15.20 DESGASTE TERMODINÁMICO
B118: E | C118: ¿ | D118: R | E118: Σ | F118: < | G118: ¡ | H118: [ | I118: Σ | J118: e | K118: ? | L118: r | M118: Σ | N118: > | O118: ! | P118: ] | Q118: Σ | X118: E | Y118: ¿ | Z118: R | AA118: Σ | AB118: < | AC118: ¡ | AD118: [ | AE118: Σ | AF118: e | AG118: ? | AH118: r | AI118: Σ | AJ118: > | AK118: ! | AL118: ] | AM118: Σ
A119: 1 | H119: 1.98 | I119: 1.98 | P119: 1.98 | Q119: 1.98 | W119: 1
A120: 2 | F120: 2.35 | I120: 2.35 | N120: 2.35 | Q120: 2.35 | W120: 2
A121: 3 | F121: 2.35 | H121: 1.98 | I121: 4.33 | N121: 2.35 | P121: 1.98 | Q121: 4.33 | W121: 3
A122: 4 | H122: 1.98 | I122: 1.98 | P122: 1.99 | Q122: 1.99 | W122: 4
A123: 5 | H123: 1.98 | I123: 1.98 | P123: 1.98 | Q123: 1.98 | W123: 5
A128: 15.06 PRISMA 6 - FACTUAL (A1 x A2)
A131: ► 15.21 DENSIDAD NETA (SDR) - PRISMA 6 - FACTUAL (A1 x A2) | W131: ► 15.22 FRECUENCIA DE IMPACTOS
B132: E | C132: ¿ | D132: R | E132: Σ | F132: < | G132: ¡ | H132: [ | I132: Σ | J132: e | K132: ? | L132: r | M132: Σ | N132: > | O132: ! | P132: ] | Q132: Σ | X132: E | Y132: ¿ | Z132: R | AA132: Σ | AB132: < | AC132: ¡ | AD132: [ | AE132: Σ | AF132: e | AG132: ? | AH132: r | AI132: Σ | AJ132: > | AK132: ! | AL132: ] | AM132: Σ
A133: 1 | D133: -1.98 | E133: -1.98 | L133: -1.98 | M133: -1.98 | W133: 1 | Z133: 1 | AA133: 1 | AH133: 1 | AI133: 1
A134: 2 | B134: 2.35 | E134: 2.35 | J134: 2.35 | M134: 2.35 | W134: 2 | X134: 1 | AA134: 1 | AF134: 1 | AI134: 1
A135: 3 | B135: 2.35 | D135: -1.98 | E135: 0.37 | J135: 2.35 | L135: -1.98 | M135: 0.37 | W135: 3 | X135: 1 | Z135: 1 | AA135: 2 | AF135: 1 | AH135: 1 | AI135: 2
A136: 4 | D136: -1.98 | E136: -1.98 | L136: -1.99 | M136: -1.99 | W136: 4 | Z136: 1 | AA136: 1 | AH136: 1 | AI136: 1
A137: 5 | D137: -1.98 | E137: -1.98 | L137: -1.98 | M137: -1.98 | W137: 5 | Z137: 1 | AA137: 1 | AH137: 1 | AI137: 1
A141: ► 15.23 DENSIDAD BRUTA (BDR) | W141: ► 15.24 DESGASTE TERMODINÁMICO
B142: E | C142: ¿ | D142: R | E142: Σ | F142: < | G142: ¡ | H142: [ | I142: Σ | J142: e | K142: ? | L142: r | M142: Σ | N142: > | O142: ! | P142: ] | Q142: Σ | X142: E | Y142: ¿ | Z142: R | AA142: Σ | AB142: < | AC142: ¡ | AD142: [ | AE142: Σ | AF142: e | AG142: ? | AH142: r | AI142: Σ | AJ142: > | AK142: ! | AL142: ] | AM142: Σ
A143: 1 | D143: 1.98 | E143: 1.98 | L143: 1.98 | M143: 1.98 | W143: 1
A144: 2 | B144: 2.35 | E144: 2.35 | J144: 2.35 | M144: 2.35 | W144: 2
A145: 3 | B145: 2.35 | D145: 1.98 | E145: 4.33 | J145: 2.35 | L145: 1.98 | M145: 4.33 | W145: 3
A146: 4 | D146: 1.98 | E146: 1.98 | L146: 1.99 | M146: 1.99 | W146: 4
A147: 5 | D147: 1.98 | E147: 1.98 | L147: 1.98 | M147: 1.98 | W147: 5

Sheet 16.Difrac_Resumen
C1: 1G1T1C Resumen Difracción
G2: Matriz ID: | H2: 1g1t1c (G2-T1-C1)
G3: Etapa: | H3: T1 - Diagnóstico Base | K3: Proyecto: | L3: Dossier Analítico NEX_ORD
C4: SIMULACIÓN IN SILICO Datos Anonimizados | G4: Motor Core: | H4: NEX_ORD Platinum v6.0 | K4: Analizado: | L4: 260829_154156
G5: Path Audit: | H5: .../05_Output/FULL_TABLES_1g1t1c.xlsx | K5: Protocolo: | L5: DOI 10.5281/zenodo.189416.1
A8: DIFRACCIÓN GLOBAL
A10: ► 16.01 DENSIDAD NETA (SDR) - ENERGÍA ÚTIL | F10: ► 16.02 FRECUENCIA DE IMPACTOS
B11: e | C11: > | D11: Σ | G11: e | H11: > | I11: Σ
A12: E | B12: -3.22 | C12: -3.22 | D12: -6.44 | F12: E | G12: 6 | H12: 6 | I12: 12
A13: <E | B13: -3.22 | C13: -3.22 | D13: -6.44 | F13: <E | G13: 6 | H13: 6 | I13: 12
A14: Σ | B14: -6.44 | C14: -6.44 | D14: -12.88 | F14: Σ | G14: 12 | H14: 12 | I14: 24
A16: ► 16.03 DENSIDAD BRUTA (BDR) - TRABAJO TOTAL | F16: ► 16.04 DESGASTE TERMODINÁMICO (BDR - |SDR|)
B17: e | C17: > | D17: Σ | G17: e | H17: > | I17: Σ
A18: E | B18: 12.6 | C18: 12.6 | D18: 25.2 | F18: E
A19: <E | B19: 12.6 | C19: 12.6 | D19: 25.2 | F19: <E
A20: Σ | B20: 25.2 | C20: 25.2 | D20: 50.4 | F20: Σ
A23: PRISMA 1 - ACTIVO (A4 x A1)
A25: ► 16.05 PRISMA 1 - ACTIVO (A4 x A1) (SDR) | F25: ► 16.06 PRISMA 1 - ACTIVO (A4 x A1) (FREQ)
B26: e | C26: > | D26: Σ | G26: e | H26: > | I26: Σ
A27: E | F27: E
A28: <E | F28: <E
A29: Σ | F29: Σ
A31: ► 16.07 PRISMA 1 - ACTIVO (A4 x A1) (BDR) | F31: ► 16.08 PRISMA 1 - ACTIVO (A4 x A1) (WEAR)
B32: e | C32: > | D32: Σ | G32: e | H32: > | I32: Σ
A33: E | F33: E
A34: <E | F34: <E
A35: Σ | F35: Σ
A38: PRISMA 2 - PASIVO (A2 x A3)
A40: ► 16.09 PRISMA 2 - PASIVO (A2 x A3) (SDR) | F40: ► 16.10 PRISMA 2 - PASIVO (A2 x A3) (FREQ)
B41: e | C41: > | D41: Σ | G41: e | H41: > | I41: Σ
A42: E | F42: E
A43: <E | F43: <E
A44: Σ | F44: Σ
A46: ► 16.11 PRISMA 2 - PASIVO (A2 x A3) (BDR) | F46: ► 16.12 PRISMA 2 - PASIVO (A2 x A3) (WEAR)
B47: e | C47: > | D47: Σ | G47: e | H47: > | I47: Σ
A48: E | F48: E
A49: <E | F49: <E
A50: Σ | F50: Σ
A53: PRISMA 3 - EXTERNO (A4 x A2)
A55: ► 16.13 PRISMA 3 - EXTERNO (A4 x A2) (SDR) | F55: ► 16.14 PRISMA 3 - EXTERNO (A4 x A2) (FREQ)
B56: e | C56: > | D56: Σ | G56: e | H56: > | I56: Σ
A57: E | F57: E
A58: <E | F58: <E
A59: Σ | F59: Σ
A61: ► 16.15 PRISMA 3 - EXTERNO (A4 x A2) (BDR) | F61: ► 16.16 PRISMA 3 - EXTERNO (A4 x A2) (WEAR)
B62: e | C62: > | D62: Σ | G62: e | H62: > | I62: Σ
A63: E | F63: E
A64: <E | F64: <E
A65: Σ | F65: Σ
A68: PRISMA 4 - INTERNO (A1 x A3)
A70: ► 16.17 PRISMA 4 - INTERNO (A1 x A3) (SDR) | F70: ► 16.18 PRISMA 4 - INTERNO (A1 x A3) (FREQ)
B71: e | C71: > | D71: Σ | G71: e | H71: > | I71: Σ
A72: E | F72: E
A73: <E | F73: <E
A74: Σ | F74: Σ
A76: ► 16.19 PRISMA 4 - INTERNO (A1 x A3) (BDR) | F76: ► 16.20 PRISMA 4 - INTERNO (A1 x A3) (WEAR)
B77: e | C77: > | D77: Σ | G77: e | H77: > | I77: Σ
A78: E | F78: E
A79: <E | F79: <E
A80: Σ | F80: Σ
A83: PRISMA 5 - PERCEPTUAL (A4 x A3)
A85: ► 16.21 PRISMA 5 - PERCEPTUAL (A4 x A3) (SDR) | F85: ► 16.22 PRISMA 5 - PERCEPTUAL (A4 x A3) (FREQ)
B86: e | C86: > | D86: Σ | G86: e | H86: > | I86: Σ
A87: E | F87: E
A88: <E | F88: <E
A89: Σ | F89: Σ
A91: ► 16.23 PRISMA 5 - PERCEPTUAL (A4 x A3) (BDR) | F91: ► 16.24 PRISMA 5 - PERCEPTUAL (A4 x A3) (WEAR)
B92: e | C92: > | D92: Σ | G92: e | H92: > | I92: Σ
A93: E | F93: E
A94: <E | F94: <E
A95: Σ | F95: Σ
A98: PRISMA 6 - FACTUAL (A1 x A2)
A100: ► 16.25 PRISMA 6 - FACTUAL (A1 x A2) (SDR) | F100: ► 16.26 PRISMA 6 - FACTUAL (A1 x A2) (FREQ)
B101: e | C101: > | D101: Σ | G101: e | H101: > | I101: Σ
A102: E | F102: E
A103: <E | F103: <E
A104: Σ | F104: Σ
A106: ► 16.27 PRISMA 6 - FACTUAL (A1 x A2) (BDR) | F106: ► 16.28 PRISMA 6 - FACTUAL (A1 x A2) (WEAR)
B107: e | C107: > | D107: Σ | G107: e | H107: > | I107: Σ
A108: E | F108: E
A109: <E | F109: <E
A110: Σ | F110: Σ

Sheet 17.Individual
C1: 1G1T1C 17.Individual
G2: Matriz ID: | H2: 1g1t1c (G2-T1-C1)
G3: Etapa: | H3: T1 - Diagnóstico Base | K3: Proyecto: | L3: Dossier Analítico NEX_ORD
C4: SIMULACIÓN IN SILICO Datos Anonimizados | G4: Motor Core: | H4: NEX_ORD Platinum v6.0 | K4: Analizado: | L4: 260829_154156
G5: Path Audit: | H5: .../05_Output/FULL_TABLES_1g1t1c.xlsx | K5: Protocolo: | L5: DOI 10.5281/zenodo.189416.1
A8: ► 17.01 FRECUENCIAS INDIVIDUALES (DA / RECIBE) | X8: ► 17.05 LEYENDA
C9: E | D9: ¿ | E9: R | F9: < | G9: ¡ | H9: [ | I9: Ee | J9: ¿? | K9: Rr | L9: <..> | M9: ¡..! | N9: [..] | O9: Er | P9: Re | Q9: <..] | R9: [..> | S9: <Ee> | T9: ¡¿?! | U9: [Rr] | X9: E | Y9: Elección
A10: 1 | B10: DA | X10: ¿ | Y10: Indiferencia
B11: RC | X11: R | Y11: Rechazo
A12: 2 | B12: DA | X12: < | Y12: Percepción de elección
B13: RC | X13: ¡ | Y13: Percepción de indiferencia
A14: 3 | B14: DA | X14: [ | Y14: Percepción de rechazo
B15: RC | X15: e | Y15: Elección recibida
A16: 4 | B16: DA | X16: ? | Y16: Indiferencia recibida
B17: RC | X17: r | Y17: Rechazo recibido
A18: 5 | B18: DA | X18: > | Y18: Percepción de elección recíproca
B19: RC | X19: ! | Y19: Percepción de indiferencia recíproca
X20: ] | Y20: Percepción de rechazo recíproca
X21: Ee | Y21: Elección mutuamente recíproca
A22: ► 17.02 INDICES INDIVIDUALES 01-16 (DA / RECIBE) | X22: Rr | Y22: Rechazo mutuamente recíproca
C23: I1 | D23: I2 | E23: I3 | F23: I4 | G23: I5 | H23: I6 | I23: I7 | J23: I8 | K23: I9 | L23: I10 | M23: I11 | N23: I12 | O23: I13 | P23: I14 | Q23: I15 | R23: I16 | X23: Er | Y23: Oposición Factual Interna: Er
A24: 1 | B24: DA | X24: Re | Y24: Oposición Factual Externa: Re
B25: RC | X25: <] | Y25: Oposición Perceptual Interna: <]
A26: 2 | B26: DA | X26: [> | Y26: Oposición Perceptual Externa: [>
B27: RC | X27: <Ee> | Y27: Elección mutua mutuamente percibida
A28: 3 | B28: DA | X28: [Rr] | Y28: Rechazo mutuo mutuamente percibido
B29: RC
A30: 4 | B30: DA
B31: RC | X31: ► 17.06 INDICES MODELO / DESCRIPCION
A32: 5 | B32: DA | X32: ID | Y32: Sigla | Z32: Descripción | AA32: Fórmula | AB32: Rango
B33: RC | X33: I1 | Y33: percep_E | Z33: EXPANSIVIDAD pE | AA33: < / n* | AB33: Rango [0, 1]
X34: I2 | Y34: Elección | Z34: EXPANSIVIDAD E | AA34: E / n* | AB34: Rango [0, 1]
X35: I3 | Y35: Repulsión | Z35: EXPANSIVIDAD R | AA35: R / n* | AB35: Rango [0, 1]
A36: ► 17.03 INDICES INDIVIDUALES 17-31 (DA / RECIBE) | X36: I4 | Y36: percep_R | Z36: EXPANSIVIDAD pR | AA36: [ / n* | AB36: Rango [0, 1]
C37: I17 | D37: I18 | E37: I19 | F37: I20 | G37: I21 | H37: I22 | I37: I23 | J37: I24 | K37: I25 | L37: I26 | M37: I27 | N37: I28 | O37: I29 | P37: I30 | Q37: I31 | X37: I5 | Y37: Real_pE | Z37: RECIPROCIDAD pE | AA37: <,> / < | AB37: Rango [0, 1]
A38: 1 | B38: DA | X38: I6 | Y38: Reci_E | Z38: RECIPROCIDAD E | AA38: Ee / E | AB38: Rango [0, 1]
B39: RC | X39: I7 | Y39: Reci_R | Z39: RECIPROCIDAD R | AA39: Rr / R | AB39: Rango [0, 1]
A40: 2 | B40: DA | X40: I8 | Y40: Real_pR | Z40: RECIPROCIDAD pR | AA40: [,] / [ | AB40: Rango [0, 1]
B41: RC | X41: I9 | Y41: REP_E | Z41: REALISMO PERCEPTUAL E | AA41: <,e / < | AB41: Rango [0, 1]
A42: 3 | B42: DA | X42: I10 | Y42: REP_pE | Z42: REALISMO PERCEPTUAL pE | AA42: <,e / e | AB42: Rango [0, 1]
B43: RC | X43: I11 | Y43: REP_pR | Z43: REALISMO PERCEPTUAL pR | AA43: [,r / r | AB43: Rango [0, 1]
A44: 4 | B44: DA | X44: I12 | Y44: REP_R | Z44: REALISMO PERCEPTUAL R | AA44: [,r / [ | AB44: Rango [0, 1]
B45: RC | X45: I13 | Y45: TrS_pE | Z45: TRANSPARENCIA SOCIAL pE | AA45: E,> / > | AB45: Rango [0, 1]
A46: 5 | B46: DA | X46: I14 | Y46: TrS_E | Z46: TRANSPARENCIA SOCIAL E | AA46: E,> / E | AB46: Rango [0, 1]
B47: RC | X47: I15 | Y47: TrS_R | Z47: TRANSPARENCIA SOCIAL R | AA47: R,] / R | AB47: Rango [0, 1]
X48: I16 | Y48: TrS_pR | Z48: TRANSPARENCIA SOCIAL pR | AA48: R,] / ] | AB48: Rango [0, 1]
X49: I17 | Y49: FaP_pE | Z49: FALSAS PERCEPCIONES pE | AA49: <,r / < | AB49: Rango [0, 1]
A50: ► 17.04 TABLA DE RECEPCION DE CADA MIEMBRO DEL GRUPO | X50: I18 | Y50: FaP_pR | Z50: FALSAS PERCEPCIONES pR | AA50: [,e / [ | AB50: Rango [0, 1]
A51: ID | C51: 1 | D51: 2 | E51: 3 | F51: 4 | G51: 5 | X51: I19 | Y51: OpS_pE | Z51: OPOSICIÓN DE SENTIMIENTOS pE | AA51: <,r / E | AB51: Rango [0, 1]
A52: 1 | B52: DA | C52: X | D52: 0BB0 | E52: 0000 | F52: 0b00 | G52: aaaa | X52: I20 | Y52: OpS_E | Z52: OPOSICIÓN DE SENTIMIENTOS E | AA52: E,r / E | AB52: Rango [0, 1]
B53: RC | C53: X | D53: 0BB0 | E53: 0000 | F53: 00c0 | G53: aaaa | X53: I21 | Y53: OpS_R | Z53: OPOSICIÓN DE SENTIMIENTOS R | AA53: R,e / R | AB53: Rango [0, 1]
A54: 2 | B54: DA | C54: 0BB0 | D54: X | E54: AAAA | F54: aaa0 | G54: 0b00 | X54: I22 | Y54: OpS_pR | Z54: OPOSICIÓN DE SENTIMIENTOS pR | AA54: [,e / R | AB54: Rango [0, 1]
B55: RC | C55: 0BB0 | D55: X | E55: AAAA | F55: 0baa | G55: 00b0 | X55: I23 | Y55: SS | Z55: ESTATUS SOCIOMÉTRICO | AA55: e / (e + r + ?) | AB55: Rango [-1, 1]
A56: 3 | B56: DA | C56: 0000 | D56: AAAA | E56: X | F56: aaaa | G56: 0bb0 | X56: I24 | Y56: LiD1 | Z56: LIDERAZGO | AA56: ... | AB56: Rango [0, 100]
B57: RC | C57: 0000 | D57: AAAA | E57: X | F57: aabb | G57: 0bc0 | X57: I25 | Y57: LiD2 | Z57: LIDERAZGO 2 | AA57: ... | AB57: Rango [0, 100]
A58: 4 | B58: DA | C58: 00c0 | D58: 0baa | E58: aabb | F58: X | G58: 0BB0 | X58: I26 | Y58: PoD1 | Z58: PODER | AA58: ... | AB58: Rango [0, 1]
B59: RC | C59: 0b00 | D59: aaa0 | E59: aaaa | F59: X | G59: 0BB0 | X59: I27 | Y59: PoD2 | Z59: PODER 2 | AA59: ... | AB59: Rango [0, 1]
A60: 5 | B60: DA | C60: aaaa | D60: 00b0 | E60: 0bc0 | F60: 0BB0 | G60: X | X60: I28 | Y60: DIAG | Z60: DIAG | AA60: ... | AB60: Rango [-100, 100]
B61: RC | C61: aaaa | D61: 0b00 | E61: 0bb0 | F61: 0BB0 | G61: X | X61: I29 | Y61: SIG_B | Z61: SIG_B | AA61: ... | AB61: Rango [0, 1]
X62: I30 | Y62: CRI | Z62: CRI | AA62: ... | AB62: Rango [0, 1]
X63: I31 | Y63: K_INF | Z63: K_INF | AA63: ... | AB63: Rango [0, ∞)
A65: ► 17.07 DENSIDAD NETA (SDR) - ENERGÍA ÚTIL - 1 | R65: ► 17.07S | W65: ► 17.08 FRECUENCIA DE IMPACTOS - 1 | AN65: ► 17.08S
B66: e | C66: ? | D66: r | E66: > | F66: ! | G66: ] | H66: e> | I66: e! | J66: e] | K66: ?> | L66: ?! | M66: ?] | N66: r> | O66: r! | P66: r] | S66: e | T66: > | X66: e | Y66: ? | Z66: r | AA66: > | AB66: ! | AC66: ] | AD66: e> | AE66: e! | AF66: e] | AG66: ?> | AH66: ?! | AI66: ?] | AJ66: r> | AK66: r! | AL66: r] | AO66: e | AP66: >
A67: E | R67: E | S67: -3.96 | T67: -3.96 | W67: E | AN67: E | AO67: 2 | AP67: 2
A68: ¿ | R68: <E | S68: -3.96 | T68: -3.96 | W68: ¿ | AN68: <E | AO68: 2 | AP68: 2
A69: R | D69: -3.96 | G69: -3.96 | P69: -3.96 | W69: R | Z69: 2 | AC69: 2 | AL69: 2
A70: < | W70: <
A71: ¡ | W71: ¡
A72: [ | D72: -3.96 | G72: -3.96 | P72: -3.96 | W72: [ | Z72: 2 | AC72: 2 | AL72: 2
A73: <E | W73: <E
A74: <¿ | W74: <¿
A75: <R | W75: <R
A76: ¡E | W76: ¡E
A77: ¡¿ | W77: ¡¿
A78: ¡R | W78: ¡R
A79: [E | W79: [E
A80: [¿ | W80: [¿
A81: [R | D81: -3.96 | G81: -3.96 | P81: -3.96 | W81: [R | Z81: 2 | AC81: 2 | AL81: 2
A85: ► 17.09 DENSIDAD BRUTA (BDR) - TRABAJO TOTAL - 1 | R85: ► 17.09S | W85: ► 17.09 DESGASTE TERMODINÁMICO (BDR - |SDR|) - 1 | AN85: ► 17.09S
B86: e | C86: ? | D86: r | E86: > | F86: ! | G86: ] | H86: e> | I86: e! | J86: e] | K86: ?> | L86: ?! | M86: ?] | N86: r> | O86: r! | P86: r] | S86: e | T86: > | X86: e | Y86: ? | Z86: r | AA86: > | AB86: ! | AC86: ] | AD86: e> | AE86: e! | AF86: e] | AG86: ?> | AH86: ?! | AI86: ?] | AJ86: r> | AK86: r! | AL86: r] | AO86: e | AP86: >
A87: E | R87: E | S87: 3.96 | T87: 3.96 | W87: E | AN87: E | AO87: 0 | AP87: 0
A88: ¿ | R88: <E | S88: 3.96 | T88: 3.96 | W88: ¿ | AN88: <E | AO88: 0 | AP88: 0
A89: R | D89: 3.96 | G89: 3.96 | P89: 3.96 | W89: R
A90: < | W90: <
A91: ¡ | W91: ¡
A92: [ | D92: 3.96 | G92: 3.96 | P92: 3.96 | W92: [
A93: <E | W93: <E
A94: <¿ | W94: <¿
A95: <R | W95: <R
A96: ¡E | W96: ¡E
A97: ¡¿ | W97: ¡¿
A98: ¡R | W98: ¡R
A99: [E | W99: [E
A100: [¿ | W100: [¿
A101: [R | D101: 3.96 | G101: 3.96 | P101: 3.96 | W101: [R
A107: ► 17.10 DENSIDAD NETA (SDR) - ENERGÍA ÚTIL - 2 | R107: ► 17.10S | W107: ► 17.11 FRECUENCIA DE IMPACTOS - 2 | AN107: ► 17.11S
B108: e | C108: ? | D108: r | E108: > | F108: ! | G108: ] | H108: e> | I108: e! | J108: e] | K108: ?> | L108: ?! | M108: ?] | N108: r> | O108: r! | P108: r] | S108: e | T108: > | X108: e | Y108: ? | Z108: r | AA108: > | AB108: ! | AC108: ] | AD108: e> | AE108: e! | AF108: e] | AG108: ?> | AH108: ?! | AI108: ?] | AJ108: r> | AK108: r! | AL108: r] | AO108: e | AP108: >
A109: E | B109: 4.69 | E109: 4.69 | H109: 4.69 | R109: E | S109: 4.69 | T109: 4.69 | W109: E | X109: 2 | AA109: 2 | AD109: 2 | AN109: E | AO109: 2 | AP109: 2
A110: ¿ | R110: <E | S110: 4.69 | T110: 4.69 | W110: ¿ | AN110: <E | AO110: 2 | AP110: 2
A111: R | W111: R
...

Sheet 18.Análisis_Espectral_AGE
C1: 1G1T1C ► 18. ANÁLISIS ESPECTRAL GENERALIZADO (AGE - SVD & FOURIER)
G2: Matriz ID: | H2: 1g1t1c (G2-T1-C1)
G3: Etapa: | H3: T1 - Diagnóstico Base | K3: Proyecto: | L3: Dossier Analítico NEX_ORD
C4: SIMULACIÓN IN SILICO Datos Anonimizados | G4: Motor Core: | H4: NEX_ORD Platinum v6.0 | K4: Analizado: | L4: 260829_154156
G5: Path Audit: | H5: .../05_Output/FULL_TABLES_1g1t1c.xlsx | K5: Protocolo: | L5: DOI 10.5281/zenodo.189416.1
A7: ► 18.01 ESPECTRO DE AUTOVALORES SINGULARES (AGE - SVD)
A8: Modo_Espectral | B8: Autovalor_Singular (λ) | C8: Varianza_Explicada_% | D8: Varianza_Acumulada_%
A9: Modo 1 (λ_1) | B9: 15.3759 | C9: 85.97 | D9: 85.97
A10: Modo 2 (λ_2) | B10: 5.3318 | C10: 10.34 | D10: 96.31
A11: Modo 3 (λ_3) | B11: 2.5076 | C11: 2.29 | D11: 98.59
A12: Modo 4 (λ_4) | B12: 1.7002 | C12: 1.05 | D12: 99.65
A13: Modo 5 (λ_5) | B13: 0.9871 | C13: 0.35 | D13: 100
A16: ► 18.02 INDICADORES SINTÉTICOS DE LA RED ESPECTRAL
A17: Radio Espectral (λ_1) | B17: 15.3759 | C17: Brecha Espectral (λ_1 - λ_2) | D17: 10.0441
A18: Energía Espectral del Grafo (Σ λ_i) | B18: 25.9026 | C18: Dimensión Efectiva k (85% Var) | D18: 1
A21: ► 18.03 FACTOR SCORES ESPECTRALES POR SUJETO (VECTORES PROPIOS)
A22: Sujeto | B22: Vektor_E1 (Dominante) | C22: Vektor_E2 (Secundario) | D22: Vektor_E3 (Terciario) | E22: Norma_Espectral_Indiv
A23: 1 | B23: -6.7959 | C23: 2.6286 | D23: 0.8553 | E23: 1
A24: 2 | B24: -7.0258 | C24: 1.7924 | D24: -1.4431 | E24: 1
A25: 3 | B25: -7.1989 | C25: 1.1463 | D25: 0.3455 | E25: 1
A26: 4 | B26: -6.7619 | C26: -2.6552 | D26: 1.41 | E26: 1
A27: 5 | B27: -6.5822 | C27: -3.153 | D27: -1.169 | E27: 1
A31: ► 18.04 MÉTRICAS DE FRECUENCIA Y FRICCIÓN ESPECTRAL (FFT / IFE%)
A32: Label | B32: F0_Base | C32: F1_Fundamental | D32: F_Alta_Friccion | E32: IFE_Pct | F32: Rank_Mean | G32: Perfil_Espectral
A33: 1 | B33: 3 | C33: 0.99595931 | D33: 0.089805595 | E33: 8.2711823 | F33: 3 | G33: Polarizado (Onda Macro)
A34: 2 | B34: 3 | C34: 0.94999591 | D34: 0.31226233 | E34: 24.738387 | F34: 3 | G34: Polarizado (Onda Macro)
A35: 3 | B35: 1.8 | C35: 0.42979223 | D35: 0.30867238 | E35: 41.799211 | F35: 1.8 | G35: Estable
A36: 4 | B36: 3.8 | C36: 0.62025911 | D36: 0.54339547 | E36: 46.697317 | F36: 3.8 | G36: Estable
A37: 5 | B37: 3.4 | C37: 0.87923235 | D37: 0.38334121 | E37: 30.361891 | F37: 3.4 | G37: Polarizado (Onda Macro)

Sheet 19.Markov
C1: 1G1T1C 19.Markov
G2: Matriz ID: | H2: 1g1t1c (G2-T1-C1)
G3: Etapa: | H3: T1 - Diagnóstico Base | K3: Proyecto: | L3: Dossier Analítico NEX_ORD
C4: SIMULACIÓN IN SILICO Datos Anonimizados | G4: Motor Core: | H4: NEX_ORD Platinum v6.0 | K4: Analizado: | L4: 260829_154156
G5: Path Audit: | H5: .../05_Output/FULL_TABLES_1g1t1c.xlsx | K5: Protocolo: | L5: DOI 10.5281/zenodo.189416.1
A7: ► 19.01 ESTADO ESTACIONARIO (MASA GRAVITACIONAL)
A8: Sujeto | B8: Masa_Gravitacional | C8: Ranking_Gravedad
A9: 3 | B9: 26.459691 | C9: 1
A10: 1 | B10: 20.729061 | C10: 2
A11: 2 | B11: 20.427366 | C11: 3
A12: 5 | B12: 17.740112 | C12: 4
A13: 4 | B13: 14.64377 | C13: 5
A16: ► 19.02 GRAFO PREDICTIVO MARKOV | E16: ► 19.04 Concepto de Masa Gravitacional
E17: El Grafo Predictivo de Markov modela la red sociométrica como un sistema dinámico donde la 'energía social' fluye probabilísticamente. La Masa Gravitacional (Estado Estacionario) identifica a los verdaderos 'atractores' del grupo: aquellos individuos hacia los que confluye la influencia a largo plazo, considerando no solo sus conexiones directas, sino el peso de quienes los eligen (efecto PageRank).
E44: ► 19.05 Interpretación Visual y Predictiva
E45: En el grafo, el tamaño y el color de los nodos (escala de calor hacia el rojo oscuro) indican su nivel de Masa Gravitacional. Los nodos mayores revelan a los líderes estructurales profundos. Las flechas muestran las rutas de influencia. Este modelo predictivo es vital para anticipar quiénes dominarán indirectamente la propagación de ideas o estados de ánimo en el seno del grupo.

Sheet 20.Ordinal C(n,n)
C1: 1G1T1C 20.Ordinal C(n,n)
G2: Matriz ID: | H2: 1g1t1c (G2-T1-C1)
G3: Etapa: | H3: T1 - Diagnóstico Base | K3: Proyecto: | L3: Dossier Analítico NEX_ORD
C4: SIMULACIÓN IN SILICO Datos Anonimizados | G4: Motor Core: | H4: NEX_ORD Platinum v6.0 | K4: Analizado: | L4: 260829_154156
G5: Path Audit: | H5: .../05_Output/FULL_TABLES_1g1t1c.xlsx | K5: Protocolo: | L5: DOI 10.5281/zenodo.189416.1
A7: ► 20.01 MATRIZ C(n, n) DE LA FUNCION INVERSA de BREVE ORDINAL
B9: 1 | C9: 2 | D9: 3 | E9: 4 | F9: 5
A10: 1 | C10: 0.57434918 | D10: 0.41524365 | E10: 0.32987698 | F10: 0.27594593
A11: 2 | B11: 0.41524365 | D11: 0.57434918 | E11: 0.27594593 | F11: 0.32987698
A12: 3 | B12: 0.57434918 | C12: 0.41524365 | E12: 0.27594593 | F12: 0.32987698
A13: 4 | B13: 0.32987698 | C13: 0.27594593 | D13: 1 | F13: 0.41524365
A14: 5 | B14: 0.27594593 | C14: 0.32987698 | D14: 0.57434918 | E14: 0.41524365
A17: ► 20.02 LIDERAZGO PONDERADO (EIGENVECTOR) | H17: ► 20.03 DESEQUILIBRIOS EMOCIONALES ASIMÉTRICOS
A19: Rango | B19: ID | E19: Centralidad Ponderada | H19: Nº | I19: Sujeto Más (Ego) | K19: Sujeto Menos (Alter) | M19: Brecha (ΔC)
A20: 1 | B20: 3 | E20: 0.26459714 | H20: 1 | I20: 4 | K20: 3 | M20: 0.72405407
A21: 2 | B21: 1 | E21: 0.20729044 | H21: 2 | I21: 5 | K21: 3 | M21: 0.2444722
A22: 3 | B22: 2 | E22: 0.20427317 | H22: 3 | I22: 1 | K22: 2 | M22: 0.15910553
A23: 4 | B23: 5 | E23: 0.17740146 | H23: 4 | I23: 3 | K23: 1 | M23: 0.15910553
A24: 5 | B24: 4 | E24: 0.14643778 | H24: 5 | I24: 2 | K24: 3 | M24: 0.15910553

Sheet 22.Física_Grupal
C1: G1T1C1 Física de lo Grupal (Termodinámica) - 1g1t1c
G2: Matriz ID: | H2: g1t1c1 (G1T1C1)
G3: Etapa: | H3: T1 - Diagnóstico Base | K3: Proyecto: | L3: Dossier Analítico NEX_ORD
C4: SIMULACIÓN IN SILICO Datos Anonimizados | G4: Motor Core: | H4: NEX_ORD v6.0 | K4: Analizado: | L4: 2026-08-29 15:41:59
G5: Path Audit: | H5: .../05_Output/Dossier_Maestro.xlsx | K5: Protocolo: | L5: DOI 10.5281/zenodo.189416.1
B7: Métricas de Termodinámica Grupal (T1)
B9: Métrica | C9: Valor | D9: Interpretación
B10: Entropía Grupal (S_g) | C10: 4.25 | D10: Medida del caos o flexibilidad relacional.
B11: Fatiga Estructural (IF_e) | C11: 85.4 | D11: Carga de tensión friccional soportada por los nodos.
B12: Ratio Térmico (S_g / IF_e) | C12: 0.0498 | D12: Equilibrio entre flexibilidad estructural y tensión.
B15: Índices Topológicos Triádicos
B17: Índice | C17: Valor
B18: Tasa de Entropía Perceptiva | C18: 82.5%
B19: Masa de Cizallamiento Triádico | C19: 35.0%
B20: Índice de Endogamia Sistémica | C20: 68.0%
B23: Diagnóstico de Sostenibilidad (T1 vs T2)
B25: Métrica | C25: Valor
B26: Coeficiente de Resiliencia (C_r) | C26: 0.12
B27: Índice de Sostenibilidad Grupal (ISG) | C27: 0.128
B28: Estado de Salud | C28: Sostenibilidad Tensionada (Amarillo)
B29: Alerta | C29: La estructura está en riesgo de colapso.
B32: Protocolo de Intervención Discreta (PID)
B34: Nivel | C34: Sugerencia de Intervención
B35: Nivel_1_Descompresion | C35: Válvula de Escape: Reducir la frecuencia de reportes o reuniones solo en el nodo afectado.
B36: Nivel_1_Descompresion | C36: Amortiguación de Impacto: Introducir un 'buffer' de tiempo entre recepción y emisión de respuesta.
B37: Nivel_1_Descompresion | C37: Fraccionamiento de Carga: Dividir la tarea del nodo saturado entre nodos adyacentes.
B38: Nivel_2_Inyeccion_Entropia | C38: Rotación de Flujo: Cambiar el canal de comunicación (ej. de asíncrono a síncrono).
B39: Nivel_2_Inyeccion_Entropia | C39: Apertura de 'A': Declarar un 'espacio ciego' sin medición de ratios pE/R temporalmente.
B40: Nivel_2_Inyeccion_Entropia | C40: Introducción de Ruido: Alterar el orden de prioridades menores para forzar recálculo de rutas.
B41: Nivel_3_Refuerzo_Resiliencia | C41: Descentralización de Nodos: Mover la toma de decisiones un peldaño hacia abajo o lateralmente.
B42: Nivel_3_Refuerzo_Resiliencia | C42: Incentivo Lateral: Fomentar interacción en malla sin pasar por el centroide principal.
B43: ALERTA_MAXIMA_RECRISTALIZACION | C43: ISG Crítico. Sugerencia: Parón técnico de 24h para reorganización estructural desde cero (Efecto 'Templado de Acero').

Sheet 21.Parámetros
C1: 1G1T1C 21.Parámetros
G2: Matriz ID: | H2: 1g1t1c (G2-T1-C1)
G3: Etapa: | H3: T1 - Diagnóstico Base | K3: Proyecto: | L3: Dossier Analítico NEX_ORD
C4: SIMULACIÓN IN SILICO Datos Anonimizados | G4: Motor Core: | H4: NEX_ORD Platinum v6.0 | K4: Analizado: | L4: 260829_154156
G5: Path Audit: | H5: .../05_Output/FULL_TABLES_1g1t1c.xlsx | K5: Protocolo: | L5: DOI 10.5281/zenodo.189416.1
A7: ► 21.01 Parámetros
A9: DATOS | B9: REAL
A10: fecha | B10: 20260103 # creación
A11: clave | B11: AG-M-1G-1T-1C-6V-16.
A12: grupos | B12: (1G), 16. # tamaños de los grupos
A13: Tiempos | B13: (1G1T), 20251115. # fechas de aplicación
A14: Criterios | B14: (1C), 'tarea' # criterios de elección
A15: Series | B15: (1G1T1C), g1t1c1
A16: Cohesion | B16: (GxTxC)
A17: Salida | B17: xlsx
A18: 6V | B18: (6), SX, ED, EC, EDU, ECO, FAM
A19: ► 16. | B19: (4,4), tem, fun, cog, afe

Sheet 23.Grasmaniano_Tríadas
C1: 1G1T1C ► 23. GRASMANIANO & TRÍADAS
G2: Matriz ID: | H2: 1g1t1c (G2-T1-C1)
G3: Etapa: | H3: T1 - Diagnóstico Base | K3: Proyecto: | L3: Dossier Analítico NEX_ORD
C4: SIMULACIÓN IN SILICO Datos Anonimizados | G4: Motor Core: | H4: NEX_ORD Platinum v6.0 | K4: Analizado: | L4: 260829_154156
G5: Path Audit: | H5: .../05_Output/FULL_TABLES_1g1t1c.xlsx | K5: Protocolo: | L5: DOI 10.5281/zenodo.189416.1
A7: ► 23.01 GEOMETRÍA DEL GRASMANIANO Gr(k,N) Y POSITROIDES
A9: Métrica / Parámetro Topológico | B9: Valor Obtenido | C9: Diagnóstico / Estado
A10: Espacio Variedad Grasmaniana | B10: Gr(2, 5) | C10: Variedad Manifold Activa
A11: Dimensión del Subespacio Vectorial | B11: 6 | C11: Dimensión k(N-k) = 6
A12: ¿Clasificación Positroide (Pura)? | B12: SÍ | C12: Cristalización Pura
A13: Índice de Coherencia Positroide (C_pos) | B13: 1 | C13: Coherencia Topológica Estructurada
A14: Fase Topológica Estructural | B14: SÓLIDO (Cristalización) | C14: Fase Ecosistémica Global
A15: Número de Violaciones Combinatorias (Cruces) | B15: 0 | C15: Fricciones en Cruces Vectoriales
A18: ► 23.02 EQUILIBRIO DE TRÍADAS (TEORÍA P-O-X Y CANON Q81)
A20: Indicador Triádico | B20: Frecuencia / Valor | C20: Interpretación Socio-Termodinámica
A21: Tríos y Pares Equilibrados (Positivos) | B21: 11 | C21: Afinidades y elecciones armónicas
A22: Tríos y Pares Desequilibrados (Tensión/Conflicto) | B22: 8 | C22: Rechazos o fricciones cruzadas
A23: Índice de Equilibrio Triádico (E_tri %) | B23: 57.894737 | C23: Proporción de balance estructural
A24: Estado de Balance Triádico (P-O-X) | B24: ESTABLE / EQUILIBRADO | C24: Equilibrio Heideriano en Q81
A27: ► 23.03 DIAGNÓSTICO TERMODINÁMICO DE JAMMING (ATRAPAMIENTO)
A29: Variable Termodinámica | B29: Magnitud | C29: Dictamen Ecosistémico
A30: Densidad Absoluta (BDR - Actividad Bruta) | B30: 36.06 | C30: Energía relacional total emitida
A31: Densidad Relativa (SDR - Estructura Cualitativa) | B31: -8.92 | C31: Sintonía vincular neta recíproca
A32: Brecha de Jamming / Ruido (Dif2 = BDR - SDR) | B32: 44.98 | C32: Nivel de interferencia sociométrica
A33: Entropía Sociométrica del Sistema (H_soc) | B33: 1.19 | C33: Dispersión entrópica de la red
A34: Diagnóstico de Jamming (Atrapamiento) | B34: DESBLOQUEADO (Unjammed) | C34: Estado de fluidez vs congestión
A37: ► 23.04 MATRIZ DE COORDENADAS Y DENSIDADES GRASMANIANAS
A39: ID Sujeto | B39: 1 | C39: 2 | D39: 3 | E39: 4 | F39: 5
A40: 1 | B40: 0.57894737 | C40: 0 | D40: 0 | E40: 0 | F40: 0
A41: 2 | B41: 0 | C41: 0.57894737 | D41: 0 | E41: 0 | F41: 0
A42: 3 | B42: 0 | C42: 0 | D42: 0.57894737 | E42: 0 | F42: 0
A43: 4 | B43: 0 | C43: 0 | D43: 0 | E43: 0.57894737 | F43: 0
A44: 5 | B44: 0 | C44: 0 | D44: 0 | E44: 0 | F44: 0.57894737
